{"All directions":{"00:00:00":{"Mon":63,"Tue":52,"Wed":62,"Thu":48,"Fri":44,"Sat":66,"Sun":78,"Workday":53,"7 Day":58,"Count":1814},"00:15:00":{"Mon":59,"Tue":51,"Wed":59,"Thu":46,"Fri":51,"Sat":64,"Sun":72,"Workday":53,"7 Day":57,"Count":1769},"00:30:00":{"Mon":46,"Tue":45,"Wed":50,"Thu":42,"Fri":46,"Sat":55,"Sun":62,"Workday":46,"7 Day":49,"Count":1529},"00:45:00":{"Mon":43,"Tue":47,"Wed":44,"Thu":43,"Fri":40,"Sat":50,"Sun":61,"Workday":43,"7 Day":47,"Count":1451},"01:00:00":{"Mon":40,"Tue":43,"Wed":46,"Thu":34,"Fri":40,"Sat":52,"Sun":47,"Workday":40,"7 Day":43,"Count":1337},"01:15:00":{"Mon":30,"Tue":32,"Wed":41,"Thu":35,"Fri":33,"Sat":40,"Sun":44,"Workday":34,"7 Day":37,"Count":1134},"01:30:00":{"Mon":27,"Tue":39,"Wed":33,"Thu":30,"Fri":28,"Sat":36,"Sun":35,"Workday":31,"7 Day":32,"Count":1007},"01:45:00":{"Mon":27,"Tue":30,"Wed":32,"Thu":34,"Fri":26,"Sat":32,"Sun":38,"Workday":30,"7 Day":31,"Count":974},"02:00:00":{"Mon":24,"Tue":25,"Wed":28,"Thu":25,"Fri":23,"Sat":29,"Sun":35,"Workday":25,"7 Day":27,"Count":836},"02:15:00":{"Mon":18,"Tue":27,"Wed":29,"Thu":22,"Fri":27,"Sat":25,"Sun":36,"Workday":25,"7 Day":26,"Count":812},"02:30:00":{"Mon":20,"Tue":26,"Wed":30,"Thu":19,"Fri":25,"Sat":25,"Sun":32,"Workday":24,"7 Day":25,"Count":774},"02:45:00":{"Mon":22,"Tue":27,"Wed":30,"Thu":24,"Fri":21,"Sat":23,"Sun":24,"Workday":25,"7 Day":24,"Count":758},"03:00:00":{"Mon":20,"Tue":22,"Wed":30,"Thu":23,"Fri":25,"Sat":27,"Sun":30,"Workday":24,"7 Day":25,"Count":787},"03:15:00":{"Mon":22,"Tue":24,"Wed":36,"Thu":25,"Fri":20,"Sat":24,"Sun":26,"Workday":25,"7 Day":25,"Count":782},"03:30:00":{"Mon":27,"Tue":32,"Wed":36,"Thu":23,"Fri":28,"Sat":23,"Sun":24,"Workday":29,"7 Day":27,"Count":848},"03:45:00":{"Mon":27,"Tue":30,"Wed":33,"Thu":26,"Fri":29,"Sat":26,"Sun":25,"Workday":29,"7 Day":28,"Count":863},"04:00:00":{"Mon":35,"Tue":30,"Wed":36,"Thu":26,"Fri":33,"Sat":28,"Sun":24,"Workday":32,"7 Day":30,"Count":931},"04:15:00":{"Mon":47,"Tue":37,"Wed":42,"Thu":29,"Fri":31,"Sat":26,"Sun":24,"Workday":37,"7 Day":33,"Count":1031},"04:30:00":{"Mon":57,"Tue":58,"Wed":59,"Thu":37,"Fri":42,"Sat":31,"Sun":29,"Workday":50,"7 Day":44,"Count":1363},"04:45:00":{"Mon":62,"Tue":62,"Wed":61,"Thu":43,"Fri":44,"Sat":36,"Sun":25,"Workday":53,"7 Day":47,"Count":1456},"05:00:00":{"Mon":78,"Tue":66,"Wed":72,"Thu":46,"Fri":55,"Sat":39,"Sun":26,"Workday":62,"7 Day":54,"Count":1671},"05:15:00":{"Mon":99,"Tue":78,"Wed":84,"Thu":54,"Fri":63,"Sat":39,"Sun":27,"Workday":74,"7 Day":63,"Count":1932},"05:30:00":{"Mon":144,"Tue":124,"Wed":133,"Thu":87,"Fri":94,"Sat":50,"Sun":30,"Workday":114,"7 Day":93,"Count":2873},"05:45:00":{"Mon":187,"Tue":154,"Wed":161,"Thu":99,"Fri":113,"Sat":50,"Sun":37,"Workday":140,"7 Day":112,"Count":3469},"06:00:00":{"Mon":271,"Tue":248,"Wed":263,"Thu":149,"Fri":175,"Sat":68,"Sun":55,"Workday":216,"7 Day":172,"Count":5302},"06:15:00":{"Mon":433,"Tue":378,"Wed":383,"Thu":253,"Fri":243,"Sat":85,"Sun":61,"Workday":330,"7 Day":257,"Count":7925},"06:30:00":{"Mon":525,"Tue":490,"Wed":462,"Thu":277,"Fri":299,"Sat":105,"Sun":72,"Workday":400,"7 Day":311,"Count":9602},"06:45:00":{"Mon":560,"Tue":483,"Wed":490,"Thu":285,"Fri":317,"Sat":115,"Sun":80,"Workday":415,"7 Day":325,"Count":10034},"07:00:00":{"Mon":560,"Tue":513,"Wed":488,"Thu":294,"Fri":319,"Sat":128,"Sun":79,"Workday":423,"7 Day":333,"Count":10270},"07:15:00":{"Mon":552,"Tue":532,"Wed":522,"Thu":328,"Fri":359,"Sat":148,"Sun":107,"Workday":448,"7 Day":357,"Count":11024},"07:30:00":{"Mon":480,"Tue":497,"Wed":541,"Thu":324,"Fri":378,"Sat":164,"Sun":97,"Workday":436,"7 Day":349,"Count":10791},"07:45:00":{"Mon":447,"Tue":483,"Wed":530,"Thu":330,"Fri":355,"Sat":163,"Sun":107,"Workday":421,"7 Day":340,"Count":10510},"08:00:00":{"Mon":472,"Tue":504,"Wed":567,"Thu":331,"Fri":362,"Sat":182,"Sun":120,"Workday":438,"7 Day":357,"Count":11026},"08:15:00":{"Mon":556,"Tue":589,"Wed":624,"Thu":370,"Fri":382,"Sat":229,"Sun":128,"Workday":493,"7 Day":405,"Count":12497},"08:30:00":{"Mon":531,"Tue":607,"Wed":592,"Thu":394,"Fri":403,"Sat":251,"Sun":161,"Workday":495,"7 Day":414,"Count":12799},"08:45:00":{"Mon":552,"Tue":555,"Wed":585,"Thu":360,"Fri":401,"Sat":263,"Sun":166,"Workday":480,"7 Day":406,"Count":12547},"09:00:00":{"Mon":470,"Tue":549,"Wed":527,"Thu":353,"Fri":352,"Sat":272,"Sun":172,"Workday":441,"7 Day":380,"Count":11760},"09:15:00":{"Mon":442,"Tue":572,"Wed":519,"Thu":361,"Fri":360,"Sat":290,"Sun":192,"Workday":443,"7 Day":387,"Count":11958},"09:30:00":{"Mon":509,"Tue":519,"Wed":514,"Thu":361,"Fri":352,"Sat":341,"Sun":230,"Workday":442,"7 Day":399,"Count":12357},"09:45:00":{"Mon":467,"Tue":468,"Wed":442,"Thu":333,"Fri":345,"Sat":362,"Sun":242,"Workday":404,"7 Day":377,"Count":11673},"10:00:00":{"Mon":510,"Tue":440,"Wed":415,"Thu":338,"Fri":339,"Sat":386,"Sun":264,"Workday":402,"7 Day":382,"Count":11835},"10:15:00":{"Mon":424,"Tue":414,"Wed":402,"Thu":334,"Fri":346,"Sat":374,"Sun":300,"Workday":380,"7 Day":369,"Count":11436},"10:30:00":{"Mon":410,"Tue":405,"Wed":390,"Thu":339,"Fri":334,"Sat":420,"Sun":324,"Workday":372,"7 Day":374,"Count":11580},"10:45:00":{"Mon":385,"Tue":377,"Wed":382,"Thu":338,"Fri":337,"Sat":435,"Sun":354,"Workday":362,"7 Day":372,"Count":11544},"11:00:00":{"Mon":392,"Tue":364,"Wed":372,"Thu":325,"Fri":368,"Sat":423,"Sun":367,"Workday":363,"7 Day":373,"Count":11559},"11:15:00":{"Mon":400,"Tue":394,"Wed":384,"Thu":340,"Fri":353,"Sat":453,"Sun":397,"Workday":372,"7 Day":388,"Count":12033},"11:30:00":{"Mon":406,"Tue":384,"Wed":395,"Thu":357,"Fri":366,"Sat":470,"Sun":477,"Workday":380,"7 Day":407,"Count":12616},"11:45:00":{"Mon":382,"Tue":384,"Wed":395,"Thu":343,"Fri":393,"Sat":491,"Sun":458,"Workday":378,"7 Day":406,"Count":12608},"12:00:00":{"Mon":390,"Tue":385,"Wed":413,"Thu":331,"Fri":386,"Sat":485,"Sun":492,"Workday":379,"7 Day":410,"Count":12736},"12:15:00":{"Mon":405,"Tue":410,"Wed":422,"Thu":333,"Fri":405,"Sat":481,"Sun":524,"Workday":393,"7 Day":424,"Count":13147},"12:30:00":{"Mon":403,"Tue":427,"Wed":451,"Thu":368,"Fri":420,"Sat":528,"Sun":554,"Workday":412,"7 Day":449,"Count":13924},"12:45:00":{"Mon":415,"Tue":405,"Wed":451,"Thu":368,"Fri":446,"Sat":497,"Sun":582,"Workday":416,"7 Day":450,"Count":13970},"13:00:00":{"Mon":424,"Tue":396,"Wed":472,"Thu":344,"Fri":436,"Sat":498,"Sun":580,"Workday":412,"7 Day":447,"Count":13876},"13:15:00":{"Mon":428,"Tue":450,"Wed":494,"Thu":377,"Fri":450,"Sat":501,"Sun":590,"Workday":438,"7 Day":467,"Count":14491},"13:30:00":{"Mon":460,"Tue":439,"Wed":458,"Thu":341,"Fri":467,"Sat":489,"Sun":604,"Workday":431,"7 Day":462,"Count":14331},"13:45:00":{"Mon":452,"Tue":448,"Wed":466,"Thu":360,"Fri":478,"Sat":499,"Sun":608,"Workday":439,"7 Day":470,"Count":14581},"14:00:00":{"Mon":473,"Tue":444,"Wed":478,"Thu":361,"Fri":491,"Sat":500,"Sun":596,"Workday":447,"7 Day":475,"Count":14726},"14:15:00":{"Mon":447,"Tue":466,"Wed":503,"Thu":365,"Fri":489,"Sat":482,"Sun":595,"Workday":452,"7 Day":475,"Count":14727},"14:30:00":{"Mon":460,"Tue":452,"Wed":503,"Thu":366,"Fri":524,"Sat":465,"Sun":572,"Workday":460,"7 Day":475,"Count":14726},"14:45:00":{"Mon":457,"Tue":459,"Wed":526,"Thu":369,"Fri":528,"Sat":456,"Sun":587,"Workday":466,"7 Day":480,"Count":14882},"15:00:00":{"Mon":472,"Tue":477,"Wed":533,"Thu":379,"Fri":591,"Sat":371,"Sun":555,"Workday":490,"7 Day":482,"Count":14483},"15:15:00":{"Mon":502,"Tue":518,"Wed":554,"Thu":380,"Fri":570,"Sat":388,"Sun":585,"Workday":502,"7 Day":497,"Count":14929},"15:30:00":{"Mon":530,"Tue":527,"Wed":587,"Thu":407,"Fri":538,"Sat":376,"Sun":603,"Workday":514,"7 Day":507,"Count":15222},"15:45:00":{"Mon":539,"Tue":570,"Wed":616,"Thu":424,"Fri":716,"Sat":506,"Sun":589,"Workday":566,"7 Day":561,"Count":16260},"16:00:00":{"Mon":589,"Tue":590,"Wed":649,"Thu":412,"Fri":716,"Sat":513,"Sun":622,"Workday":583,"7 Day":578,"Count":16778},"16:15:00":{"Mon":599,"Tue":624,"Wed":699,"Thu":435,"Fri":730,"Sat":536,"Sun":640,"Workday":609,"7 Day":603,"Count":17488},"16:30:00":{"Mon":642,"Tue":686,"Wed":702,"Thu":448,"Fri":696,"Sat":508,"Sun":635,"Workday":626,"7 Day":610,"Count":17717},"16:45:00":{"Mon":656,"Tue":693,"Wed":739,"Thu":467,"Fri":715,"Sat":544,"Sun":632,"Workday":645,"7 Day":629,"Count":18244},"17:00:00":{"Mon":625,"Tue":700,"Wed":714,"Thu":474,"Fri":655,"Sat":555,"Sun":607,"Workday":626,"7 Day":613,"Count":17798},"17:15:00":{"Mon":665,"Tue":711,"Wed":680,"Thu":456,"Fri":567,"Sat":537,"Sun":652,"Workday":606,"7 Day":603,"Count":18094},"17:30:00":{"Mon":651,"Tue":710,"Wed":714,"Thu":464,"Fri":548,"Sat":493,"Sun":654,"Workday":607,"7 Day":598,"Count":17948},"17:45:00":{"Mon":642,"Tue":652,"Wed":703,"Thu":441,"Fri":538,"Sat":471,"Sun":634,"Workday":586,"7 Day":576,"Count":17307},"18:00:00":{"Mon":636,"Tue":657,"Wed":708,"Thu":462,"Fri":511,"Sat":483,"Sun":647,"Workday":585,"7 Day":579,"Count":17389},"18:15:00":{"Mon":620,"Tue":613,"Wed":676,"Thu":427,"Fri":494,"Sat":441,"Sun":612,"Workday":557,"7 Day":548,"Count":16460},"18:30:00":{"Mon":554,"Tue":532,"Wed":642,"Thu":404,"Fri":487,"Sat":410,"Sun":595,"Workday":517,"7 Day":513,"Count":15390},"18:45:00":{"Mon":524,"Tue":524,"Wed":630,"Thu":345,"Fri":465,"Sat":371,"Sun":585,"Workday":489,"7 Day":486,"Count":14585},"19:00:00":{"Mon":419,"Tue":472,"Wed":530,"Thu":328,"Fri":416,"Sat":350,"Sun":532,"Workday":427,"7 Day":431,"Count":12927},"19:15:00":{"Mon":386,"Tue":419,"Wed":527,"Thu":324,"Fri":397,"Sat":320,"Sun":546,"Workday":406,"7 Day":414,"Count":12395},"19:30:00":{"Mon":330,"Tue":340,"Wed":464,"Thu":274,"Fri":376,"Sat":309,"Sun":494,"Workday":354,"7 Day":368,"Count":10999},"19:45:00":{"Mon":290,"Tue":314,"Wed":375,"Thu":265,"Fri":330,"Sat":281,"Sun":484,"Workday":313,"7 Day":333,"Count":9951},"20:00:00":{"Mon":262,"Tue":296,"Wed":330,"Thu":296,"Fri":325,"Sat":281,"Sun":455,"Workday":303,"7 Day":321,"Count":9604},"20:15:00":{"Mon":246,"Tue":268,"Wed":326,"Thu":234,"Fri":298,"Sat":257,"Sun":443,"Workday":274,"7 Day":296,"Count":8822},"20:30:00":{"Mon":232,"Tue":242,"Wed":295,"Thu":202,"Fri":257,"Sat":228,"Sun":398,"Workday":244,"7 Day":264,"Count":7882},"20:45:00":{"Mon":220,"Tue":227,"Wed":255,"Thu":178,"Fri":225,"Sat":202,"Sun":364,"Workday":219,"7 Day":238,"Count":7089},"21:00:00":{"Mon":199,"Tue":216,"Wed":247,"Thu":165,"Fri":204,"Sat":176,"Sun":336,"Workday":204,"7 Day":219,"Count":6547},"21:15:00":{"Mon":187,"Tue":203,"Wed":241,"Thu":148,"Fri":186,"Sat":172,"Sun":293,"Workday":191,"7 Day":203,"Count":6053},"21:30:00":{"Mon":178,"Tue":198,"Wed":224,"Thu":146,"Fri":152,"Sat":158,"Sun":253,"Workday":177,"7 Day":185,"Count":5543},"21:45:00":{"Mon":162,"Tue":188,"Wed":199,"Thu":140,"Fri":149,"Sat":156,"Sun":225,"Workday":165,"7 Day":173,"Count":5166},"22:00:00":{"Mon":150,"Tue":163,"Wed":185,"Thu":120,"Fri":133,"Sat":127,"Sun":198,"Workday":148,"7 Day":152,"Count":4562},"22:15:00":{"Mon":146,"Tue":145,"Wed":167,"Thu":112,"Fri":126,"Sat":115,"Sun":176,"Workday":137,"7 Day":140,"Count":4188},"22:30:00":{"Mon":117,"Tue":143,"Wed":146,"Thu":109,"Fri":133,"Sat":97,"Sun":153,"Workday":129,"7 Day":128,"Count":3833},"22:45:00":{"Mon":102,"Tue":112,"Wed":135,"Thu":107,"Fri":125,"Sat":88,"Sun":135,"Workday":116,"7 Day":115,"Count":3444},"23:00:00":{"Mon":92,"Tue":114,"Wed":130,"Thu":91,"Fri":116,"Sat":95,"Sun":113,"Workday":108,"7 Day":107,"Count":3210},"23:15:00":{"Mon":86,"Tue":98,"Wed":115,"Thu":78,"Fri":103,"Sat":97,"Sun":97,"Workday":96,"7 Day":96,"Count":2885},"23:30:00":{"Mon":78,"Tue":73,"Wed":82,"Thu":59,"Fri":83,"Sat":88,"Sun":78,"Workday":75,"7 Day":77,"Count":2306},"23:45:00":{"Mon":52,"Tue":51,"Wed":62,"Thu":54,"Fri":73,"Sat":80,"Sun":66,"Workday":59,"7 Day":63,"Count":1876},"07-19":{"Mon":24010,"Tue":24518,"Wed":25774,"Thu":17961,"Fri":22261,"Sat":19628,"Sun":21476,"Workday":22625,"7 Day":22040,"Count":670632},"06-22":{"Mon":28910,"Tue":29501,"Wed":31385,"Thu":21626,"Fri":26609,"Sat":22893,"Sun":26568,"Workday":27263,"7 Day":26549,"Count":806473},"06-24":{"Mon":29733,"Tue":30401,"Wed":32408,"Thu":22355,"Fri":27501,"Sat":23680,"Sun":27584,"Workday":28131,"7 Day":27426,"Count":832777},"00-24":{"Mon":30956,"Tue":31565,"Wed":33676,"Thu":23278,"Fri":28486,"Sat":24578,"Sun":28474,"Workday":29229,"7 Day":28466,"Count":864978},"am Peak":{"Mon":"06:30:00","Tue":"08:15:00","Wed":"08:00:00","Thu":"08:15:00","Fri":"08:00:00","Sat":"11:00:00","Sun":"11:00:00","Workday":"08:15:00","7 Day":"08:15:00","Count":""},"Peak Volume":{"Mon":649,"Tue":703,"Wed":713,"Thu":465,"Fri":714,"Sat":536,"Sun":647,"Workday":626,"7 Day":614,"Count":null},"pm Peak":{"Mon":"16:45:00","Tue":"16:45:00","Wed":"16:15:00","Thu":"16:45:00","Fri":"15:45:00","Sat":"16:30:00","Sun":"17:15:00","Workday":"16:15:00","7 Day":"16:30:00","Count":""}},"All Eastbound":{"00:00:00":{"Mon":21,"Tue":20,"Wed":21,"Thu":17,"Fri":17,"Sat":23,"Sun":30,"Workday":19,"7 Day":21,"Count":658},"00:15:00":{"Mon":23,"Tue":16,"Wed":19,"Thu":13,"Fri":16,"Sat":21,"Sun":30,"Workday":17,"7 Day":19,"Count":602},"00:30:00":{"Mon":11,"Tue":14,"Wed":17,"Thu":13,"Fri":16,"Sat":16,"Sun":18,"Workday":14,"7 Day":15,"Count":465},"00:45:00":{"Mon":16,"Tue":16,"Wed":16,"Thu":15,"Fri":11,"Sat":14,"Sun":17,"Workday":15,"7 Day":15,"Count":465},"01:00:00":{"Mon":14,"Tue":14,"Wed":16,"Thu":13,"Fri":13,"Sat":16,"Sun":16,"Workday":14,"7 Day":15,"Count":454},"01:15:00":{"Mon":9,"Tue":10,"Wed":16,"Thu":12,"Fri":11,"Sat":13,"Sun":14,"Workday":11,"7 Day":12,"Count":370},"01:30:00":{"Mon":6,"Tue":13,"Wed":10,"Thu":11,"Fri":9,"Sat":8,"Sun":13,"Workday":10,"7 Day":10,"Count":305},"01:45:00":{"Mon":10,"Tue":10,"Wed":13,"Thu":10,"Fri":7,"Sat":6,"Sun":12,"Workday":10,"7 Day":10,"Count":301},"02:00:00":{"Mon":6,"Tue":5,"Wed":8,"Thu":7,"Fri":6,"Sat":9,"Sun":12,"Workday":6,"7 Day":7,"Count":229},"02:15:00":{"Mon":7,"Tue":9,"Wed":9,"Thu":9,"Fri":7,"Sat":9,"Sun":12,"Workday":8,"7 Day":9,"Count":278},"02:30:00":{"Mon":7,"Tue":8,"Wed":9,"Thu":5,"Fri":11,"Sat":10,"Sun":12,"Workday":8,"7 Day":9,"Count":271},"02:45:00":{"Mon":11,"Tue":10,"Wed":9,"Thu":12,"Fri":9,"Sat":9,"Sun":10,"Workday":10,"7 Day":10,"Count":308},"03:00:00":{"Mon":7,"Tue":8,"Wed":13,"Thu":9,"Fri":10,"Sat":10,"Sun":16,"Workday":9,"7 Day":10,"Count":316},"03:15:00":{"Mon":11,"Tue":10,"Wed":18,"Thu":11,"Fri":9,"Sat":12,"Sun":14,"Workday":12,"7 Day":12,"Count":373},"03:30:00":{"Mon":16,"Tue":20,"Wed":20,"Thu":14,"Fri":14,"Sat":12,"Sun":13,"Workday":17,"7 Day":15,"Count":475},"03:45:00":{"Mon":18,"Tue":19,"Wed":19,"Thu":17,"Fri":17,"Sat":15,"Sun":14,"Workday":18,"7 Day":17,"Count":528},"04:00:00":{"Mon":21,"Tue":18,"Wed":20,"Thu":14,"Fri":20,"Sat":14,"Sun":13,"Workday":19,"7 Day":17,"Count":532},"04:15:00":{"Mon":30,"Tue":22,"Wed":30,"Thu":18,"Fri":17,"Sat":13,"Sun":13,"Workday":23,"7 Day":20,"Count":626},"04:30:00":{"Mon":38,"Tue":39,"Wed":38,"Thu":23,"Fri":25,"Sat":19,"Sun":16,"Workday":32,"7 Day":28,"Count":862},"04:45:00":{"Mon":42,"Tue":40,"Wed":36,"Thu":26,"Fri":26,"Sat":21,"Sun":13,"Workday":34,"7 Day":29,"Count":894},"05:00:00":{"Mon":53,"Tue":43,"Wed":46,"Thu":28,"Fri":35,"Sat":23,"Sun":14,"Workday":40,"7 Day":34,"Count":1053},"05:15:00":{"Mon":63,"Tue":52,"Wed":51,"Thu":32,"Fri":40,"Sat":22,"Sun":15,"Workday":46,"7 Day":39,"Count":1192},"05:30:00":{"Mon":92,"Tue":93,"Wed":94,"Thu":60,"Fri":65,"Sat":31,"Sun":18,"Workday":79,"7 Day":64,"Count":1969},"05:45:00":{"Mon":134,"Tue":112,"Wed":119,"Thu":69,"Fri":78,"Sat":29,"Sun":21,"Workday":100,"7 Day":78,"Count":2421},"06:00:00":{"Mon":212,"Tue":195,"Wed":208,"Thu":118,"Fri":135,"Sat":46,"Sun":35,"Workday":169,"7 Day":133,"Count":4096},"06:15:00":{"Mon":341,"Tue":310,"Wed":309,"Thu":192,"Fri":190,"Sat":60,"Sun":39,"Workday":262,"7 Day":201,"Count":6211},"06:30:00":{"Mon":420,"Tue":391,"Wed":362,"Thu":211,"Fri":231,"Sat":66,"Sun":46,"Workday":314,"7 Day":240,"Count":7413},"06:45:00":{"Mon":412,"Tue":361,"Wed":373,"Thu":211,"Fri":236,"Sat":70,"Sun":48,"Workday":310,"7 Day":238,"Count":7357},"07:00:00":{"Mon":388,"Tue":357,"Wed":346,"Thu":199,"Fri":224,"Sat":76,"Sun":40,"Workday":295,"7 Day":228,"Count":7026},"07:15:00":{"Mon":354,"Tue":338,"Wed":346,"Thu":202,"Fri":244,"Sat":90,"Sun":54,"Workday":290,"7 Day":228,"Count":7051},"07:30:00":{"Mon":274,"Tue":286,"Wed":330,"Thu":193,"Fri":249,"Sat":92,"Sun":56,"Workday":262,"7 Day":209,"Count":6459},"07:45:00":{"Mon":240,"Tue":273,"Wed":308,"Thu":188,"Fri":211,"Sat":87,"Sun":52,"Workday":240,"7 Day":192,"Count":5923},"08:00:00":{"Mon":246,"Tue":277,"Wed":345,"Thu":187,"Fri":212,"Sat":100,"Sun":65,"Workday":248,"7 Day":202,"Count":6226},"08:15:00":{"Mon":298,"Tue":310,"Wed":353,"Thu":211,"Fri":202,"Sat":138,"Sun":64,"Workday":269,"7 Day":222,"Count":6859},"08:30:00":{"Mon":258,"Tue":317,"Wed":322,"Thu":211,"Fri":218,"Sat":144,"Sun":78,"Workday":261,"7 Day":219,"Count":6764},"08:45:00":{"Mon":308,"Tue":303,"Wed":328,"Thu":197,"Fri":232,"Sat":148,"Sun":79,"Workday":269,"7 Day":225,"Count":6962},"09:00:00":{"Mon":260,"Tue":332,"Wed":319,"Thu":206,"Fri":203,"Sat":148,"Sun":91,"Workday":258,"7 Day":220,"Count":6786},"09:15:00":{"Mon":233,"Tue":361,"Wed":314,"Thu":208,"Fri":216,"Sat":154,"Sun":105,"Workday":262,"7 Day":225,"Count":6948},"09:30:00":{"Mon":283,"Tue":311,"Wed":298,"Thu":203,"Fri":207,"Sat":175,"Sun":126,"Workday":255,"7 Day":226,"Count":6999},"09:45:00":{"Mon":271,"Tue":267,"Wed":246,"Thu":185,"Fri":188,"Sat":188,"Sun":115,"Workday":228,"7 Day":207,"Count":6408},"10:00:00":{"Mon":313,"Tue":242,"Wed":233,"Thu":174,"Fri":179,"Sat":199,"Sun":132,"Workday":223,"7 Day":208,"Count":6432},"10:15:00":{"Mon":233,"Tue":228,"Wed":219,"Thu":179,"Fri":166,"Sat":197,"Sun":155,"Workday":202,"7 Day":195,"Count":6052},"10:30:00":{"Mon":224,"Tue":216,"Wed":206,"Thu":179,"Fri":160,"Sat":222,"Sun":154,"Workday":194,"7 Day":194,"Count":6003},"10:45:00":{"Mon":210,"Tue":202,"Wed":195,"Thu":169,"Fri":163,"Sat":220,"Sun":174,"Workday":186,"7 Day":190,"Count":5880},"11:00:00":{"Mon":210,"Tue":181,"Wed":206,"Thu":173,"Fri":180,"Sat":217,"Sun":173,"Workday":189,"7 Day":191,"Count":5930},"11:15:00":{"Mon":208,"Tue":202,"Wed":204,"Thu":173,"Fri":173,"Sat":227,"Sun":199,"Workday":190,"7 Day":197,"Count":6121},"11:30:00":{"Mon":217,"Tue":197,"Wed":207,"Thu":183,"Fri":171,"Sat":229,"Sun":238,"Workday":193,"7 Day":205,"Count":6351},"11:45:00":{"Mon":192,"Tue":190,"Wed":196,"Thu":168,"Fri":183,"Sat":246,"Sun":228,"Workday":185,"7 Day":200,"Count":6210},"12:00:00":{"Mon":200,"Tue":194,"Wed":213,"Thu":165,"Fri":177,"Sat":230,"Sun":242,"Workday":188,"7 Day":202,"Count":6258},"12:15:00":{"Mon":199,"Tue":200,"Wed":210,"Thu":164,"Fri":189,"Sat":230,"Sun":261,"Workday":191,"7 Day":206,"Count":6394},"12:30:00":{"Mon":203,"Tue":205,"Wed":233,"Thu":180,"Fri":199,"Sat":260,"Sun":278,"Workday":203,"7 Day":221,"Count":6872},"12:45:00":{"Mon":213,"Tue":211,"Wed":229,"Thu":180,"Fri":201,"Sat":244,"Sun":301,"Workday":205,"7 Day":224,"Count":6942},"13:00:00":{"Mon":209,"Tue":197,"Wed":233,"Thu":163,"Fri":198,"Sat":251,"Sun":301,"Workday":198,"7 Day":220,"Count":6825},"13:15:00":{"Mon":215,"Tue":233,"Wed":244,"Thu":182,"Fri":197,"Sat":226,"Sun":300,"Workday":212,"7 Day":225,"Count":6993},"13:30:00":{"Mon":229,"Tue":226,"Wed":222,"Thu":165,"Fri":205,"Sat":242,"Sun":319,"Workday":207,"7 Day":227,"Count":7047},"13:45:00":{"Mon":228,"Tue":225,"Wed":224,"Thu":175,"Fri":208,"Sat":242,"Sun":324,"Workday":210,"7 Day":229,"Count":7124},"14:00:00":{"Mon":243,"Tue":220,"Wed":235,"Thu":174,"Fri":213,"Sat":245,"Sun":313,"Workday":215,"7 Day":232,"Count":7200},"14:15:00":{"Mon":220,"Tue":234,"Wed":240,"Thu":175,"Fri":211,"Sat":233,"Sun":319,"Workday":214,"7 Day":230,"Count":7149},"14:30:00":{"Mon":215,"Tue":213,"Wed":242,"Thu":171,"Fri":238,"Sat":218,"Sun":314,"Workday":215,"7 Day":228,"Count":7069},"14:45:00":{"Mon":205,"Tue":227,"Wed":252,"Thu":174,"Fri":232,"Sat":212,"Sun":318,"Workday":217,"7 Day":229,"Count":7095},"15:00:00":{"Mon":231,"Tue":221,"Wed":245,"Thu":185,"Fri":238,"Sat":172,"Sun":299,"Workday":223,"7 Day":227,"Count":6788},"15:15:00":{"Mon":240,"Tue":236,"Wed":257,"Thu":173,"Fri":233,"Sat":185,"Sun":317,"Workday":225,"7 Day":233,"Count":6969},"15:30:00":{"Mon":236,"Tue":233,"Wed":256,"Thu":185,"Fri":227,"Sat":178,"Sun":319,"Workday":226,"7 Day":232,"Count":6952},"15:45:00":{"Mon":237,"Tue":257,"Wed":267,"Thu":181,"Fri":311,"Sat":243,"Sun":327,"Workday":247,"7 Day":258,"Count":7475},"16:00:00":{"Mon":259,"Tue":259,"Wed":274,"Thu":183,"Fri":303,"Sat":250,"Sun":355,"Workday":252,"7 Day":266,"Count":7708},"16:15:00":{"Mon":243,"Tue":256,"Wed":299,"Thu":186,"Fri":307,"Sat":247,"Sun":365,"Workday":255,"7 Day":270,"Count":7801},"16:30:00":{"Mon":270,"Tue":281,"Wed":286,"Thu":184,"Fri":290,"Sat":244,"Sun":352,"Workday":258,"7 Day":270,"Count":7808},"16:45:00":{"Mon":250,"Tue":270,"Wed":290,"Thu":192,"Fri":297,"Sat":253,"Sun":355,"Workday":257,"7 Day":270,"Count":7827},"17:00:00":{"Mon":236,"Tue":274,"Wed":286,"Thu":194,"Fri":277,"Sat":266,"Sun":339,"Workday":251,"7 Day":265,"Count":7678},"17:15:00":{"Mon":250,"Tue":274,"Wed":285,"Thu":186,"Fri":231,"Sat":242,"Sun":367,"Workday":242,"7 Day":260,"Count":7761},"17:30:00":{"Mon":230,"Tue":271,"Wed":282,"Thu":187,"Fri":218,"Sat":237,"Sun":368,"Workday":234,"7 Day":254,"Count":7572},"17:45:00":{"Mon":228,"Tue":234,"Wed":277,"Thu":181,"Fri":220,"Sat":218,"Sun":362,"Workday":225,"7 Day":244,"Count":7281},"18:00:00":{"Mon":227,"Tue":250,"Wed":277,"Thu":186,"Fri":220,"Sat":226,"Sun":373,"Workday":230,"7 Day":250,"Count":7449},"18:15:00":{"Mon":200,"Tue":235,"Wed":258,"Thu":163,"Fri":210,"Sat":212,"Sun":355,"Workday":211,"7 Day":232,"Count":6910},"18:30:00":{"Mon":203,"Tue":212,"Wed":229,"Thu":169,"Fri":201,"Sat":200,"Sun":338,"Workday":201,"7 Day":220,"Count":6576},"18:45:00":{"Mon":194,"Tue":191,"Wed":240,"Thu":147,"Fri":187,"Sat":184,"Sun":335,"Workday":190,"7 Day":210,"Count":6248},"19:00:00":{"Mon":182,"Tue":181,"Wed":214,"Thu":135,"Fri":173,"Sat":168,"Sun":314,"Workday":175,"7 Day":194,"Count":5778},"19:15:00":{"Mon":158,"Tue":165,"Wed":205,"Thu":132,"Fri":157,"Sat":158,"Sun":329,"Workday":162,"7 Day":185,"Count":5508},"19:30:00":{"Mon":142,"Tue":140,"Wed":172,"Thu":110,"Fri":144,"Sat":147,"Sun":297,"Workday":140,"7 Day":164,"Count":4867},"19:45:00":{"Mon":118,"Tue":123,"Wed":146,"Thu":99,"Fri":126,"Sat":130,"Sun":293,"Workday":121,"7 Day":147,"Count":4360},"20:00:00":{"Mon":116,"Tue":125,"Wed":140,"Thu":111,"Fri":132,"Sat":141,"Sun":274,"Workday":125,"7 Day":148,"Count":4404},"20:15:00":{"Mon":107,"Tue":109,"Wed":126,"Thu":90,"Fri":119,"Sat":131,"Sun":272,"Workday":110,"7 Day":136,"Count":4027},"20:30:00":{"Mon":104,"Tue":100,"Wed":120,"Thu":83,"Fri":110,"Sat":110,"Sun":250,"Workday":103,"7 Day":125,"Count":3704},"20:45:00":{"Mon":104,"Tue":112,"Wed":106,"Thu":75,"Fri":92,"Sat":92,"Sun":229,"Workday":96,"7 Day":115,"Count":3406},"21:00:00":{"Mon":92,"Tue":94,"Wed":107,"Thu":68,"Fri":84,"Sat":83,"Sun":221,"Workday":88,"7 Day":106,"Count":3146},"21:15:00":{"Mon":90,"Tue":82,"Wed":105,"Thu":60,"Fri":80,"Sat":80,"Sun":189,"Workday":82,"7 Day":97,"Count":2881},"21:30:00":{"Mon":83,"Tue":83,"Wed":104,"Thu":56,"Fri":60,"Sat":66,"Sun":172,"Workday":75,"7 Day":88,"Count":2604},"21:45:00":{"Mon":77,"Tue":83,"Wed":90,"Thu":52,"Fri":65,"Sat":76,"Sun":142,"Workday":72,"7 Day":83,"Count":2457},"22:00:00":{"Mon":62,"Tue":70,"Wed":74,"Thu":48,"Fri":62,"Sat":60,"Sun":123,"Workday":62,"7 Day":71,"Count":2108},"22:15:00":{"Mon":62,"Tue":61,"Wed":66,"Thu":43,"Fri":50,"Sat":54,"Sun":113,"Workday":55,"7 Day":63,"Count":1884},"22:30:00":{"Mon":50,"Tue":60,"Wed":61,"Thu":43,"Fri":51,"Sat":42,"Sun":94,"Workday":52,"7 Day":57,"Count":1701},"22:45:00":{"Mon":45,"Tue":42,"Wed":54,"Thu":38,"Fri":39,"Sat":38,"Sun":75,"Workday":43,"7 Day":47,"Count":1401},"23:00:00":{"Mon":40,"Tue":50,"Wed":48,"Thu":31,"Fri":38,"Sat":40,"Sun":66,"Workday":41,"7 Day":45,"Count":1328},"23:15:00":{"Mon":28,"Tue":37,"Wed":41,"Thu":25,"Fri":33,"Sat":35,"Sun":48,"Workday":32,"7 Day":35,"Count":1047},"23:30:00":{"Mon":32,"Tue":28,"Wed":30,"Thu":22,"Fri":27,"Sat":28,"Sun":36,"Workday":27,"7 Day":29,"Count":861},"23:45:00":{"Mon":22,"Tue":20,"Wed":24,"Thu":20,"Fri":24,"Sat":24,"Sun":29,"Workday":22,"7 Day":23,"Count":694},"07-19":{"Mon":11532,"Tue":11928,"Wed":12611,"Thu":8737,"Fri":10422,"Sat":9687,"Sun":11498,"Workday":10901,"7 Day":10815,"Count":329161},"06-22":{"Mon":14288,"Tue":14583,"Wed":15500,"Thu":10538,"Fri":12556,"Sat":11312,"Sun":14648,"Workday":13304,"7 Day":13215,"Count":401380},"06-24":{"Mon":14630,"Tue":14951,"Wed":15896,"Thu":10809,"Fri":12880,"Sat":11634,"Sun":15233,"Workday":13640,"7 Day":13585,"Count":412404},"00-24":{"Mon":15298,"Tue":15573,"Wed":16565,"Thu":11266,"Fri":13369,"Sat":12008,"Sun":15609,"Workday":14212,"7 Day":14100,"Count":428351},"am Peak":{"Mon":"06:30:00","Tue":"06:30:00","Wed":"06:30:00","Thu":"08:15:00","Fri":"06:45:00","Sat":"11:00:00","Sun":"11:00:00","Workday":"06:30:00","7 Day":"06:30:00","Count":""},"Peak Volume":{"Mon":256,"Tue":275,"Wed":290,"Thu":190,"Fri":303,"Sat":252,"Sun":368,"Workday":255,"7 Day":269,"Count":null},"pm Peak":{"Mon":"16:00:00","Tue":"16:30:00","Wed":"16:15:00","Thu":"16:45:00","Fri":"15:45:00","Sat":"16:15:00","Sun":"17:15:00","Workday":"16:00:00","7 Day":"16:00:00","Count":""}},"All Westbound":{"00:00:00":{"Mon":41,"Tue":32,"Wed":41,"Thu":31,"Fri":27,"Sat":43,"Sun":48,"Workday":34,"7 Day":37,"Count":1156},"00:15:00":{"Mon":36,"Tue":35,"Wed":40,"Thu":33,"Fri":35,"Sat":43,"Sun":42,"Workday":36,"7 Day":38,"Count":1167},"00:30:00":{"Mon":35,"Tue":31,"Wed":34,"Thu":29,"Fri":30,"Sat":40,"Sun":44,"Workday":31,"7 Day":34,"Count":1064},"00:45:00":{"Mon":26,"Tue":32,"Wed":28,"Thu":28,"Fri":29,"Sat":36,"Sun":44,"Workday":29,"7 Day":32,"Count":986},"01:00:00":{"Mon":26,"Tue":28,"Wed":30,"Thu":22,"Fri":27,"Sat":36,"Sun":31,"Workday":26,"7 Day":28,"Count":883},"01:15:00":{"Mon":21,"Tue":23,"Wed":25,"Thu":23,"Fri":23,"Sat":27,"Sun":30,"Workday":23,"7 Day":25,"Count":764},"01:30:00":{"Mon":21,"Tue":26,"Wed":23,"Thu":19,"Fri":19,"Sat":28,"Sun":22,"Workday":21,"7 Day":23,"Count":702},"01:45:00":{"Mon":16,"Tue":20,"Wed":20,"Thu":24,"Fri":19,"Sat":26,"Sun":26,"Workday":20,"7 Day":22,"Count":673},"02:00:00":{"Mon":17,"Tue":20,"Wed":21,"Thu":19,"Fri":17,"Sat":20,"Sun":24,"Workday":19,"7 Day":20,"Count":607},"02:15:00":{"Mon":11,"Tue":18,"Wed":20,"Thu":13,"Fri":20,"Sat":16,"Sun":23,"Workday":16,"7 Day":17,"Count":534},"02:30:00":{"Mon":13,"Tue":18,"Wed":21,"Thu":14,"Fri":15,"Sat":15,"Sun":20,"Workday":16,"7 Day":16,"Count":503},"02:45:00":{"Mon":11,"Tue":17,"Wed":21,"Thu":12,"Fri":12,"Sat":14,"Sun":14,"Workday":15,"7 Day":15,"Count":450},"03:00:00":{"Mon":13,"Tue":15,"Wed":17,"Thu":15,"Fri":16,"Sat":17,"Sun":14,"Workday":15,"7 Day":15,"Count":471},"03:15:00":{"Mon":11,"Tue":14,"Wed":18,"Thu":14,"Fri":11,"Sat":12,"Sun":12,"Workday":14,"7 Day":13,"Count":409},"03:30:00":{"Mon":11,"Tue":12,"Wed":16,"Thu":9,"Fri":14,"Sat":11,"Sun":11,"Workday":12,"7 Day":12,"Count":373},"03:45:00":{"Mon":8,"Tue":11,"Wed":14,"Thu":9,"Fri":12,"Sat":11,"Sun":11,"Workday":11,"7 Day":11,"Count":335},"04:00:00":{"Mon":13,"Tue":11,"Wed":15,"Thu":13,"Fri":13,"Sat":14,"Sun":11,"Workday":13,"7 Day":13,"Count":399},"04:15:00":{"Mon":17,"Tue":14,"Wed":11,"Thu":11,"Fri":14,"Sat":13,"Sun":11,"Workday":14,"7 Day":13,"Count":405},"04:30:00":{"Mon":18,"Tue":19,"Wed":21,"Thu":14,"Fri":17,"Sat":12,"Sun":13,"Workday":18,"7 Day":16,"Count":501},"04:45:00":{"Mon":20,"Tue":22,"Wed":25,"Thu":17,"Fri":17,"Sat":16,"Sun":12,"Workday":20,"7 Day":18,"Count":562},"05:00:00":{"Mon":25,"Tue":23,"Wed":26,"Thu":18,"Fri":20,"Sat":16,"Sun":12,"Workday":22,"7 Day":20,"Count":618},"05:15:00":{"Mon":36,"Tue":26,"Wed":33,"Thu":22,"Fri":23,"Sat":18,"Sun":12,"Workday":27,"7 Day":24,"Count":740},"05:30:00":{"Mon":52,"Tue":32,"Wed":38,"Thu":27,"Fri":28,"Sat":19,"Sun":12,"Workday":35,"7 Day":29,"Count":904},"05:45:00":{"Mon":54,"Tue":42,"Wed":42,"Thu":30,"Fri":35,"Sat":21,"Sun":16,"Workday":40,"7 Day":34,"Count":1048},"06:00:00":{"Mon":59,"Tue":53,"Wed":54,"Thu":31,"Fri":40,"Sat":22,"Sun":20,"Workday":46,"7 Day":39,"Count":1206},"06:15:00":{"Mon":92,"Tue":68,"Wed":74,"Thu":61,"Fri":52,"Sat":24,"Sun":22,"Workday":68,"7 Day":55,"Count":1714},"06:30:00":{"Mon":106,"Tue":99,"Wed":100,"Thu":66,"Fri":67,"Sat":39,"Sun":26,"Workday":86,"7 Day":71,"Count":2189},"06:45:00":{"Mon":147,"Tue":122,"Wed":117,"Thu":73,"Fri":81,"Sat":46,"Sun":33,"Workday":105,"7 Day":87,"Count":2677},"07:00:00":{"Mon":172,"Tue":156,"Wed":142,"Thu":95,"Fri":95,"Sat":51,"Sun":39,"Workday":129,"7 Day":105,"Count":3244},"07:15:00":{"Mon":198,"Tue":193,"Wed":176,"Thu":126,"Fri":115,"Sat":58,"Sun":52,"Workday":158,"7 Day":129,"Count":3973},"07:30:00":{"Mon":206,"Tue":211,"Wed":210,"Thu":132,"Fri":128,"Sat":72,"Sun":40,"Workday":173,"7 Day":140,"Count":4332},"07:45:00":{"Mon":208,"Tue":210,"Wed":222,"Thu":142,"Fri":144,"Sat":76,"Sun":55,"Workday":181,"7 Day":148,"Count":4587},"08:00:00":{"Mon":226,"Tue":227,"Wed":222,"Thu":144,"Fri":150,"Sat":82,"Sun":56,"Workday":189,"7 Day":155,"Count":4800},"08:15:00":{"Mon":258,"Tue":279,"Wed":271,"Thu":159,"Fri":179,"Sat":91,"Sun":64,"Workday":224,"7 Day":183,"Count":5638},"08:30:00":{"Mon":273,"Tue":290,"Wed":270,"Thu":183,"Fri":185,"Sat":107,"Sun":83,"Workday":235,"7 Day":195,"Count":6035},"08:45:00":{"Mon":243,"Tue":252,"Wed":256,"Thu":162,"Fri":168,"Sat":115,"Sun":88,"Workday":212,"7 Day":181,"Count":5585},"09:00:00":{"Mon":210,"Tue":218,"Wed":208,"Thu":146,"Fri":150,"Sat":125,"Sun":82,"Workday":183,"7 Day":161,"Count":4974},"09:15:00":{"Mon":208,"Tue":211,"Wed":205,"Thu":153,"Fri":144,"Sat":136,"Sun":86,"Workday":181,"7 Day":162,"Count":5010},"09:30:00":{"Mon":226,"Tue":208,"Wed":215,"Thu":158,"Fri":146,"Sat":166,"Sun":103,"Workday":187,"7 Day":173,"Count":5358},"09:45:00":{"Mon":195,"Tue":200,"Wed":195,"Thu":148,"Fri":157,"Sat":174,"Sun":127,"Workday":177,"7 Day":170,"Count":5265},"10:00:00":{"Mon":198,"Tue":199,"Wed":182,"Thu":164,"Fri":161,"Sat":187,"Sun":133,"Workday":179,"7 Day":174,"Count":5403},"10:15:00":{"Mon":192,"Tue":186,"Wed":183,"Thu":154,"Fri":180,"Sat":177,"Sun":145,"Workday":178,"7 Day":174,"Count":5384},"10:30:00":{"Mon":186,"Tue":189,"Wed":184,"Thu":160,"Fri":174,"Sat":197,"Sun":170,"Workday":178,"7 Day":180,"Count":5577},"10:45:00":{"Mon":175,"Tue":176,"Wed":187,"Thu":169,"Fri":174,"Sat":215,"Sun":180,"Workday":176,"7 Day":183,"Count":5664},"11:00:00":{"Mon":182,"Tue":183,"Wed":166,"Thu":152,"Fri":187,"Sat":206,"Sun":194,"Workday":174,"7 Day":181,"Count":5629},"11:15:00":{"Mon":192,"Tue":192,"Wed":180,"Thu":167,"Fri":180,"Sat":226,"Sun":198,"Workday":181,"7 Day":191,"Count":5912},"11:30:00":{"Mon":190,"Tue":187,"Wed":188,"Thu":174,"Fri":195,"Sat":241,"Sun":240,"Workday":187,"7 Day":202,"Count":6265},"11:45:00":{"Mon":190,"Tue":193,"Wed":200,"Thu":174,"Fri":209,"Sat":245,"Sun":230,"Workday":193,"7 Day":206,"Count":6398},"12:00:00":{"Mon":190,"Tue":191,"Wed":200,"Thu":166,"Fri":209,"Sat":256,"Sun":250,"Workday":191,"7 Day":209,"Count":6478},"12:15:00":{"Mon":205,"Tue":210,"Wed":213,"Thu":169,"Fri":216,"Sat":252,"Sun":264,"Workday":202,"7 Day":218,"Count":6753},"12:30:00":{"Mon":200,"Tue":222,"Wed":218,"Thu":188,"Fri":221,"Sat":268,"Sun":276,"Workday":209,"7 Day":227,"Count":7052},"12:45:00":{"Mon":202,"Tue":194,"Wed":222,"Thu":189,"Fri":244,"Sat":253,"Sun":281,"Workday":211,"7 Day":226,"Count":7028},"13:00:00":{"Mon":214,"Tue":199,"Wed":238,"Thu":180,"Fri":238,"Sat":246,"Sun":279,"Workday":214,"7 Day":227,"Count":7051},"13:15:00":{"Mon":213,"Tue":218,"Wed":250,"Thu":195,"Fri":253,"Sat":275,"Sun":290,"Workday":226,"7 Day":242,"Count":7498},"13:30:00":{"Mon":231,"Tue":213,"Wed":236,"Thu":176,"Fri":262,"Sat":247,"Sun":284,"Workday":223,"7 Day":235,"Count":7284},"13:45:00":{"Mon":224,"Tue":223,"Wed":242,"Thu":185,"Fri":271,"Sat":257,"Sun":284,"Workday":229,"7 Day":240,"Count":7457},"14:00:00":{"Mon":231,"Tue":223,"Wed":244,"Thu":187,"Fri":279,"Sat":255,"Sun":282,"Workday":233,"7 Day":243,"Count":7526},"14:15:00":{"Mon":226,"Tue":232,"Wed":263,"Thu":190,"Fri":279,"Sat":250,"Sun":275,"Workday":238,"7 Day":244,"Count":7578},"14:30:00":{"Mon":245,"Tue":239,"Wed":262,"Thu":196,"Fri":285,"Sat":247,"Sun":258,"Workday":245,"7 Day":247,"Count":7657},"14:45:00":{"Mon":253,"Tue":232,"Wed":274,"Thu":195,"Fri":296,"Sat":244,"Sun":269,"Workday":250,"7 Day":251,"Count":7787},"15:00:00":{"Mon":241,"Tue":256,"Wed":288,"Thu":194,"Fri":353,"Sat":199,"Sun":256,"Workday":267,"7 Day":256,"Count":7695},"15:15:00":{"Mon":262,"Tue":282,"Wed":296,"Thu":207,"Fri":337,"Sat":202,"Sun":268,"Workday":276,"7 Day":265,"Count":7960},"15:30:00":{"Mon":294,"Tue":294,"Wed":331,"Thu":222,"Fri":311,"Sat":198,"Sun":284,"Workday":288,"7 Day":275,"Count":8270},"15:45:00":{"Mon":302,"Tue":313,"Wed":348,"Thu":243,"Fri":405,"Sat":263,"Sun":262,"Workday":318,"7 Day":302,"Count":8785},"16:00:00":{"Mon":330,"Tue":331,"Wed":375,"Thu":230,"Fri":413,"Sat":264,"Sun":267,"Workday":331,"7 Day":312,"Count":9070},"16:15:00":{"Mon":356,"Tue":369,"Wed":400,"Thu":249,"Fri":422,"Sat":289,"Sun":275,"Workday":354,"7 Day":333,"Count":9687},"16:30:00":{"Mon":372,"Tue":405,"Wed":416,"Thu":265,"Fri":406,"Sat":264,"Sun":284,"Workday":368,"7 Day":341,"Count":9909},"16:45:00":{"Mon":405,"Tue":422,"Wed":448,"Thu":275,"Fri":417,"Sat":291,"Sun":276,"Workday":388,"7 Day":358,"Count":10417},"17:00:00":{"Mon":389,"Tue":427,"Wed":428,"Thu":280,"Fri":377,"Sat":290,"Sun":268,"Workday":376,"7 Day":348,"Count":10120},"17:15:00":{"Mon":415,"Tue":437,"Wed":395,"Thu":270,"Fri":336,"Sat":294,"Sun":284,"Workday":364,"7 Day":343,"Count":10333},"17:30:00":{"Mon":422,"Tue":439,"Wed":432,"Thu":277,"Fri":330,"Sat":256,"Sun":287,"Workday":373,"7 Day":344,"Count":10376},"17:45:00":{"Mon":414,"Tue":418,"Wed":427,"Thu":260,"Fri":317,"Sat":253,"Sun":272,"Workday":360,"7 Day":332,"Count":10026},"18:00:00":{"Mon":409,"Tue":407,"Wed":431,"Thu":275,"Fri":291,"Sat":256,"Sun":274,"Workday":355,"7 Day":330,"Count":9940},"18:15:00":{"Mon":421,"Tue":378,"Wed":418,"Thu":265,"Fri":284,"Sat":229,"Sun":257,"Workday":346,"7 Day":316,"Count":9550},"18:30:00":{"Mon":351,"Tue":320,"Wed":413,"Thu":235,"Fri":287,"Sat":210,"Sun":256,"Workday":316,"7 Day":292,"Count":8814},"18:45:00":{"Mon":330,"Tue":333,"Wed":390,"Thu":198,"Fri":278,"Sat":186,"Sun":250,"Workday":300,"7 Day":276,"Count":8337},"19:00:00":{"Mon":237,"Tue":290,"Wed":316,"Thu":193,"Fri":243,"Sat":182,"Sun":218,"Workday":252,"7 Day":237,"Count":7149},"19:15:00":{"Mon":228,"Tue":253,"Wed":322,"Thu":192,"Fri":240,"Sat":163,"Sun":217,"Workday":244,"7 Day":229,"Count":6887},"19:30:00":{"Mon":188,"Tue":201,"Wed":292,"Thu":164,"Fri":232,"Sat":161,"Sun":197,"Workday":214,"7 Day":204,"Count":6132},"19:45:00":{"Mon":172,"Tue":191,"Wed":228,"Thu":166,"Fri":204,"Sat":152,"Sun":192,"Workday":192,"7 Day":186,"Count":5591},"20:00:00":{"Mon":146,"Tue":171,"Wed":190,"Thu":185,"Fri":193,"Sat":140,"Sun":180,"Workday":178,"7 Day":173,"Count":5200},"20:15:00":{"Mon":138,"Tue":158,"Wed":200,"Thu":144,"Fri":179,"Sat":127,"Sun":171,"Workday":164,"7 Day":160,"Count":4795},"20:30:00":{"Mon":128,"Tue":142,"Wed":175,"Thu":120,"Fri":147,"Sat":118,"Sun":148,"Workday":142,"7 Day":139,"Count":4178},"20:45:00":{"Mon":116,"Tue":115,"Wed":149,"Thu":103,"Fri":133,"Sat":109,"Sun":136,"Workday":123,"7 Day":123,"Count":3683},"21:00:00":{"Mon":107,"Tue":122,"Wed":140,"Thu":98,"Fri":120,"Sat":93,"Sun":115,"Workday":117,"7 Day":113,"Count":3401},"21:15:00":{"Mon":98,"Tue":122,"Wed":136,"Thu":88,"Fri":106,"Sat":92,"Sun":104,"Workday":109,"7 Day":106,"Count":3172},"21:30:00":{"Mon":96,"Tue":115,"Wed":121,"Thu":91,"Fri":93,"Sat":92,"Sun":81,"Workday":102,"7 Day":98,"Count":2939},"21:45:00":{"Mon":85,"Tue":105,"Wed":108,"Thu":88,"Fri":84,"Sat":80,"Sun":83,"Workday":94,"7 Day":90,"Count":2709},"22:00:00":{"Mon":88,"Tue":93,"Wed":111,"Thu":72,"Fri":72,"Sat":67,"Sun":75,"Workday":86,"7 Day":82,"Count":2454},"22:15:00":{"Mon":84,"Tue":84,"Wed":102,"Thu":69,"Fri":76,"Sat":61,"Sun":63,"Workday":82,"7 Day":76,"Count":2304},"22:30:00":{"Mon":67,"Tue":83,"Wed":85,"Thu":65,"Fri":83,"Sat":54,"Sun":59,"Workday":76,"7 Day":71,"Count":2132},"22:45:00":{"Mon":57,"Tue":70,"Wed":81,"Thu":69,"Fri":85,"Sat":50,"Sun":60,"Workday":73,"7 Day":68,"Count":2043},"23:00:00":{"Mon":52,"Tue":64,"Wed":82,"Thu":60,"Fri":77,"Sat":54,"Sun":47,"Workday":67,"7 Day":62,"Count":1882},"23:15:00":{"Mon":58,"Tue":61,"Wed":74,"Thu":53,"Fri":70,"Sat":62,"Sun":49,"Workday":63,"7 Day":61,"Count":1838},"23:30:00":{"Mon":47,"Tue":44,"Wed":52,"Thu":37,"Fri":56,"Sat":60,"Sun":42,"Workday":47,"7 Day":48,"Count":1445},"23:45:00":{"Mon":30,"Tue":31,"Wed":38,"Thu":34,"Fri":49,"Sat":56,"Sun":37,"Workday":37,"7 Day":40,"Count":1182},"07-19":{"Mon":12478,"Tue":12590,"Wed":13162,"Thu":9224,"Fri":11839,"Sat":9941,"Sun":9978,"Workday":11724,"7 Day":11225,"Count":341471},"06-22":{"Mon":14621,"Tue":14918,"Wed":15886,"Thu":11087,"Fri":14053,"Sat":11581,"Sun":11920,"Workday":13959,"7 Day":13334,"Count":405093},"06-24":{"Mon":15104,"Tue":15450,"Wed":16512,"Thu":11546,"Fri":14621,"Sat":12047,"Sun":12351,"Workday":14490,"7 Day":13842,"Count":420373},"00-24":{"Mon":15658,"Tue":15992,"Wed":17110,"Thu":12011,"Fri":15117,"Sat":12570,"Sun":12865,"Workday":15017,"7 Day":14366,"Count":436627},"am Peak":{"Mon":"08:00:00","Tue":"08:00:00","Wed":"08:00:00","Thu":"11:00:00","Fri":"11:00:00","Sat":"11:00:00","Sun":"11:00:00","Workday":"08:00:00","7 Day":"11:00:00","Count":""},"Peak Volume":{"Mon":416,"Tue":431,"Wed":427,"Thu":276,"Fri":415,"Sat":285,"Sun":285,"Workday":375,"7 Day":348,"Count":null},"pm Peak":{"Mon":"17:30:00","Tue":"16:45:00","Wed":"17:30:00","Thu":"16:45:00","Fri":"16:00:00","Sat":"16:30:00","Sun":"13:15:00","Workday":"16:45:00","7 Day":"16:45:00","Count":""}},"Eastbound 1":{"00:00:00":{"Mon":20,"Tue":17,"Wed":20,"Thu":15,"Fri":15,"Sat":20,"Sun":27,"Workday":17,"7 Day":19,"Count":580},"00:15:00":{"Mon":21,"Tue":12,"Wed":16,"Thu":12,"Fri":14,"Sat":18,"Sun":26,"Workday":15,"7 Day":17,"Count":522},"00:30:00":{"Mon":11,"Tue":13,"Wed":16,"Thu":12,"Fri":15,"Sat":14,"Sun":17,"Workday":13,"7 Day":14,"Count":430},"00:45:00":{"Mon":15,"Tue":14,"Wed":15,"Thu":14,"Fri":10,"Sat":12,"Sun":15,"Workday":14,"7 Day":14,"Count":420},"01:00:00":{"Mon":14,"Tue":13,"Wed":16,"Thu":12,"Fri":12,"Sat":14,"Sun":15,"Workday":13,"7 Day":13,"Count":418},"01:15:00":{"Mon":8,"Tue":9,"Wed":15,"Thu":11,"Fri":10,"Sat":11,"Sun":13,"Workday":11,"7 Day":11,"Count":349},"01:30:00":{"Mon":5,"Tue":12,"Wed":10,"Thu":10,"Fri":8,"Sat":8,"Sun":13,"Workday":9,"7 Day":9,"Count":289},"01:45:00":{"Mon":9,"Tue":10,"Wed":12,"Thu":9,"Fri":7,"Sat":6,"Sun":12,"Workday":9,"7 Day":9,"Count":279},"02:00:00":{"Mon":6,"Tue":5,"Wed":7,"Thu":6,"Fri":6,"Sat":8,"Sun":10,"Workday":6,"7 Day":7,"Count":215},"02:15:00":{"Mon":7,"Tue":8,"Wed":8,"Thu":9,"Fri":6,"Sat":9,"Sun":11,"Workday":8,"7 Day":8,"Count":258},"02:30:00":{"Mon":7,"Tue":7,"Wed":8,"Thu":4,"Fri":10,"Sat":9,"Sun":11,"Workday":8,"7 Day":8,"Count":258},"02:45:00":{"Mon":10,"Tue":10,"Wed":9,"Thu":11,"Fri":8,"Sat":9,"Sun":9,"Workday":10,"7 Day":9,"Count":292},"03:00:00":{"Mon":7,"Tue":7,"Wed":12,"Thu":8,"Fri":9,"Sat":10,"Sun":14,"Workday":9,"7 Day":9,"Count":294},"03:15:00":{"Mon":10,"Tue":10,"Wed":18,"Thu":10,"Fri":8,"Sat":12,"Sun":13,"Workday":11,"7 Day":11,"Count":350},"03:30:00":{"Mon":15,"Tue":18,"Wed":18,"Thu":12,"Fri":13,"Sat":11,"Sun":12,"Workday":15,"7 Day":14,"Count":429},"03:45:00":{"Mon":17,"Tue":17,"Wed":16,"Thu":16,"Fri":16,"Sat":15,"Sun":13,"Workday":16,"7 Day":16,"Count":488},"04:00:00":{"Mon":20,"Tue":17,"Wed":19,"Thu":13,"Fri":17,"Sat":13,"Sun":12,"Workday":17,"7 Day":16,"Count":486},"04:15:00":{"Mon":27,"Tue":20,"Wed":27,"Thu":16,"Fri":15,"Sat":12,"Sun":12,"Workday":21,"7 Day":18,"Count":567},"04:30:00":{"Mon":33,"Tue":31,"Wed":32,"Thu":21,"Fri":21,"Sat":18,"Sun":14,"Workday":27,"7 Day":24,"Count":742},"04:45:00":{"Mon":36,"Tue":31,"Wed":29,"Thu":23,"Fri":23,"Sat":18,"Sun":13,"Workday":28,"7 Day":24,"Count":752},"05:00:00":{"Mon":40,"Tue":35,"Wed":38,"Thu":23,"Fri":27,"Sat":20,"Sun":13,"Workday":32,"7 Day":28,"Count":851},"05:15:00":{"Mon":47,"Tue":39,"Wed":40,"Thu":26,"Fri":32,"Sat":19,"Sun":14,"Workday":36,"7 Day":30,"Count":942},"05:30:00":{"Mon":63,"Tue":61,"Wed":66,"Thu":44,"Fri":46,"Sat":27,"Sun":16,"Workday":55,"7 Day":46,"Count":1406},"05:45:00":{"Mon":80,"Tue":74,"Wed":72,"Thu":47,"Fri":53,"Sat":25,"Sun":19,"Workday":64,"7 Day":52,"Count":1606},"06:00:00":{"Mon":109,"Tue":103,"Wed":102,"Thu":64,"Fri":74,"Sat":37,"Sun":31,"Workday":88,"7 Day":73,"Count":2252},"06:15:00":{"Mon":126,"Tue":116,"Wed":115,"Thu":79,"Fri":86,"Sat":45,"Sun":31,"Workday":102,"7 Day":84,"Count":2604},"06:30:00":{"Mon":141,"Tue":134,"Wed":130,"Thu":80,"Fri":98,"Sat":48,"Sun":39,"Workday":114,"7 Day":94,"Count":2907},"06:45:00":{"Mon":142,"Tue":137,"Wed":136,"Thu":83,"Fri":98,"Sat":52,"Sun":39,"Workday":117,"7 Day":96,"Count":2981},"07:00:00":{"Mon":140,"Tue":139,"Wed":134,"Thu":82,"Fri":99,"Sat":54,"Sun":34,"Workday":116,"7 Day":96,"Count":2971},"07:15:00":{"Mon":133,"Tue":136,"Wed":134,"Thu":94,"Fri":106,"Sat":60,"Sun":47,"Workday":119,"7 Day":100,"Count":3101},"07:30:00":{"Mon":117,"Tue":125,"Wed":142,"Thu":88,"Fri":111,"Sat":61,"Sun":46,"Workday":115,"7 Day":98,"Count":3020},"07:45:00":{"Mon":119,"Tue":120,"Wed":138,"Thu":90,"Fri":99,"Sat":64,"Sun":44,"Workday":112,"7 Day":96,"Count":2954},"08:00:00":{"Mon":113,"Tue":119,"Wed":145,"Thu":89,"Fri":100,"Sat":70,"Sun":54,"Workday":112,"7 Day":98,"Count":3024},"08:15:00":{"Mon":136,"Tue":142,"Wed":154,"Thu":104,"Fri":94,"Sat":88,"Sun":51,"Workday":123,"7 Day":109,"Count":3359},"08:30:00":{"Mon":126,"Tue":146,"Wed":147,"Thu":100,"Fri":107,"Sat":92,"Sun":65,"Workday":123,"7 Day":111,"Count":3431},"08:45:00":{"Mon":142,"Tue":141,"Wed":151,"Thu":95,"Fri":111,"Sat":94,"Sun":63,"Workday":126,"7 Day":113,"Count":3489},"09:00:00":{"Mon":125,"Tue":154,"Wed":150,"Thu":104,"Fri":99,"Sat":96,"Sun":67,"Workday":124,"7 Day":112,"Count":3478},"09:15:00":{"Mon":107,"Tue":168,"Wed":151,"Thu":108,"Fri":105,"Sat":99,"Sun":81,"Workday":126,"7 Day":116,"Count":3580},"09:30:00":{"Mon":134,"Tue":152,"Wed":143,"Thu":109,"Fri":105,"Sat":102,"Sun":94,"Workday":127,"7 Day":119,"Count":3673},"09:45:00":{"Mon":125,"Tue":130,"Wed":128,"Thu":104,"Fri":103,"Sat":105,"Sun":86,"Workday":117,"7 Day":111,"Count":3438},"10:00:00":{"Mon":153,"Tue":132,"Wed":126,"Thu":101,"Fri":100,"Sat":114,"Sun":90,"Workday":121,"7 Day":116,"Count":3584},"10:15:00":{"Mon":121,"Tue":122,"Wed":122,"Thu":97,"Fri":99,"Sat":113,"Sun":108,"Workday":111,"7 Day":111,"Count":3437},"10:30:00":{"Mon":126,"Tue":123,"Wed":121,"Thu":99,"Fri":94,"Sat":118,"Sun":104,"Workday":111,"7 Day":112,"Count":3457},"10:45:00":{"Mon":115,"Tue":117,"Wed":113,"Thu":99,"Fri":93,"Sat":118,"Sun":118,"Workday":107,"7 Day":110,"Count":3409},"11:00:00":{"Mon":124,"Tue":112,"Wed":123,"Thu":98,"Fri":104,"Sat":118,"Sun":120,"Workday":111,"7 Day":113,"Count":3515},"11:15:00":{"Mon":118,"Tue":112,"Wed":121,"Thu":102,"Fri":98,"Sat":122,"Sun":128,"Workday":109,"7 Day":114,"Count":3531},"11:30:00":{"Mon":122,"Tue":116,"Wed":118,"Thu":101,"Fri":101,"Sat":122,"Sun":142,"Workday":111,"7 Day":117,"Count":3617},"11:45:00":{"Mon":116,"Tue":116,"Wed":109,"Thu":100,"Fri":102,"Sat":124,"Sun":135,"Workday":108,"7 Day":114,"Count":3533},"12:00:00":{"Mon":117,"Tue":118,"Wed":118,"Thu":99,"Fri":99,"Sat":120,"Sun":140,"Workday":109,"7 Day":115,"Count":3564},"12:15:00":{"Mon":117,"Tue":118,"Wed":118,"Thu":96,"Fri":100,"Sat":118,"Sun":144,"Workday":109,"7 Day":115,"Count":3559},"12:30:00":{"Mon":116,"Tue":120,"Wed":122,"Thu":103,"Fri":105,"Sat":128,"Sun":151,"Workday":112,"7 Day":120,"Count":3715},"12:45:00":{"Mon":122,"Tue":123,"Wed":126,"Thu":95,"Fri":105,"Sat":122,"Sun":156,"Workday":113,"7 Day":120,"Count":3721},"13:00:00":{"Mon":118,"Tue":118,"Wed":128,"Thu":93,"Fri":106,"Sat":118,"Sun":156,"Workday":111,"7 Day":118,"Count":3662},"13:15:00":{"Mon":120,"Tue":122,"Wed":131,"Thu":101,"Fri":96,"Sat":117,"Sun":154,"Workday":113,"7 Day":119,"Count":3682},"13:30:00":{"Mon":124,"Tue":123,"Wed":127,"Thu":95,"Fri":107,"Sat":123,"Sun":158,"Workday":114,"7 Day":121,"Count":3749},"13:45:00":{"Mon":130,"Tue":129,"Wed":124,"Thu":94,"Fri":106,"Sat":124,"Sun":169,"Workday":115,"7 Day":123,"Count":3825},"14:00:00":{"Mon":127,"Tue":120,"Wed":122,"Thu":97,"Fri":110,"Sat":124,"Sun":158,"Workday":114,"7 Day":121,"Count":3761},"14:15:00":{"Mon":122,"Tue":123,"Wed":121,"Thu":94,"Fri":105,"Sat":122,"Sun":164,"Workday":112,"7 Day":120,"Count":3720},"14:30:00":{"Mon":112,"Tue":119,"Wed":121,"Thu":94,"Fri":112,"Sat":118,"Sun":165,"Workday":111,"7 Day":119,"Count":3691},"14:45:00":{"Mon":117,"Tue":126,"Wed":132,"Thu":96,"Fri":108,"Sat":113,"Sun":163,"Workday":115,"7 Day":120,"Count":3738},"15:00:00":{"Mon":123,"Tue":124,"Wed":125,"Thu":98,"Fri":110,"Sat":98,"Sun":157,"Workday":115,"7 Day":119,"Count":3551},"15:15:00":{"Mon":127,"Tue":131,"Wed":130,"Thu":94,"Fri":110,"Sat":100,"Sun":165,"Workday":117,"7 Day":122,"Count":3637},"15:30:00":{"Mon":123,"Tue":124,"Wed":126,"Thu":98,"Fri":113,"Sat":94,"Sun":161,"Workday":116,"7 Day":119,"Count":3570},"15:45:00":{"Mon":122,"Tue":130,"Wed":132,"Thu":96,"Fri":146,"Sat":127,"Sun":165,"Workday":124,"7 Day":130,"Count":3769},"16:00:00":{"Mon":130,"Tue":131,"Wed":132,"Thu":96,"Fri":148,"Sat":146,"Sun":170,"Workday":126,"7 Day":135,"Count":3906},"16:15:00":{"Mon":126,"Tue":132,"Wed":143,"Thu":97,"Fri":139,"Sat":134,"Sun":162,"Workday":126,"7 Day":132,"Count":3828},"16:30:00":{"Mon":135,"Tue":140,"Wed":142,"Thu":100,"Fri":137,"Sat":137,"Sun":172,"Workday":130,"7 Day":137,"Count":3959},"16:45:00":{"Mon":130,"Tue":134,"Wed":136,"Thu":98,"Fri":137,"Sat":136,"Sun":157,"Workday":126,"7 Day":132,"Count":3814},"17:00:00":{"Mon":129,"Tue":132,"Wed":140,"Thu":102,"Fri":136,"Sat":144,"Sun":158,"Workday":127,"7 Day":134,"Count":3868},"17:15:00":{"Mon":134,"Tue":136,"Wed":140,"Thu":99,"Fri":116,"Sat":131,"Sun":165,"Workday":123,"7 Day":130,"Count":3898},"17:30:00":{"Mon":122,"Tue":132,"Wed":136,"Thu":97,"Fri":105,"Sat":130,"Sun":162,"Workday":117,"7 Day":125,"Count":3739},"17:45:00":{"Mon":122,"Tue":120,"Wed":136,"Thu":96,"Fri":112,"Sat":129,"Sun":162,"Workday":116,"7 Day":124,"Count":3713},"18:00:00":{"Mon":118,"Tue":128,"Wed":133,"Thu":99,"Fri":105,"Sat":128,"Sun":164,"Workday":115,"7 Day":124,"Count":3705},"18:15:00":{"Mon":119,"Tue":120,"Wed":127,"Thu":88,"Fri":99,"Sat":122,"Sun":152,"Workday":109,"7 Day":117,"Count":3491},"18:30:00":{"Mon":109,"Tue":110,"Wed":118,"Thu":89,"Fri":100,"Sat":113,"Sun":152,"Workday":104,"7 Day":112,"Count":3353},"18:45:00":{"Mon":104,"Tue":105,"Wed":121,"Thu":77,"Fri":94,"Sat":102,"Sun":144,"Workday":99,"7 Day":106,"Count":3154},"19:00:00":{"Mon":100,"Tue":97,"Wed":108,"Thu":78,"Fri":88,"Sat":99,"Sun":133,"Workday":93,"7 Day":100,"Count":2977},"19:15:00":{"Mon":92,"Tue":90,"Wed":104,"Thu":73,"Fri":82,"Sat":96,"Sun":133,"Workday":87,"7 Day":95,"Count":2840},"19:30:00":{"Mon":85,"Tue":84,"Wed":92,"Thu":68,"Fri":82,"Sat":94,"Sun":133,"Workday":81,"7 Day":91,"Count":2697},"19:45:00":{"Mon":73,"Tue":76,"Wed":86,"Thu":61,"Fri":75,"Sat":85,"Sun":130,"Workday":74,"7 Day":83,"Count":2478},"20:00:00":{"Mon":77,"Tue":80,"Wed":85,"Thu":68,"Fri":79,"Sat":89,"Sun":128,"Workday":78,"7 Day":86,"Count":2576},"20:15:00":{"Mon":74,"Tue":70,"Wed":78,"Thu":57,"Fri":72,"Sat":84,"Sun":132,"Workday":70,"7 Day":81,"Count":2404},"20:30:00":{"Mon":71,"Tue":65,"Wed":77,"Thu":53,"Fri":67,"Sat":75,"Sun":118,"Workday":66,"7 Day":75,"Count":2222},"20:45:00":{"Mon":69,"Tue":76,"Wed":71,"Thu":51,"Fri":59,"Sat":69,"Sun":119,"Workday":64,"7 Day":73,"Count":2171},"21:00:00":{"Mon":64,"Tue":66,"Wed":72,"Thu":48,"Fri":58,"Sat":59,"Sun":117,"Workday":61,"7 Day":68,"Count":2039},"21:15:00":{"Mon":58,"Tue":57,"Wed":69,"Thu":43,"Fri":55,"Sat":57,"Sun":105,"Workday":56,"7 Day":63,"Count":1872},"21:30:00":{"Mon":58,"Tue":56,"Wed":71,"Thu":43,"Fri":45,"Sat":52,"Sun":99,"Workday":54,"7 Day":60,"Count":1780},"21:45:00":{"Mon":56,"Tue":58,"Wed":62,"Thu":40,"Fri":46,"Sat":58,"Sun":91,"Workday":52,"7 Day":58,"Count":1731},"22:00:00":{"Mon":46,"Tue":49,"Wed":52,"Thu":37,"Fri":44,"Sat":49,"Sun":79,"Workday":45,"7 Day":51,"Count":1514},"22:15:00":{"Mon":47,"Tue":44,"Wed":49,"Thu":35,"Fri":39,"Sat":44,"Sun":78,"Workday":42,"7 Day":48,"Count":1418},"22:30:00":{"Mon":40,"Tue":44,"Wed":48,"Thu":34,"Fri":37,"Sat":35,"Sun":64,"Workday":40,"7 Day":43,"Count":1278},"22:45:00":{"Mon":35,"Tue":34,"Wed":42,"Thu":29,"Fri":32,"Sat":30,"Sun":57,"Workday":34,"7 Day":37,"Count":1098},"23:00:00":{"Mon":32,"Tue":39,"Wed":39,"Thu":27,"Fri":32,"Sat":35,"Sun":50,"Workday":33,"7 Day":36,"Count":1075},"23:15:00":{"Mon":25,"Tue":30,"Wed":35,"Thu":22,"Fri":27,"Sat":30,"Sun":39,"Workday":27,"7 Day":29,"Count":880},"23:30:00":{"Mon":27,"Tue":26,"Wed":26,"Thu":18,"Fri":23,"Sat":24,"Sun":31,"Workday":24,"7 Day":25,"Count":740},"23:45:00":{"Mon":20,"Tue":17,"Wed":20,"Thu":18,"Fri":21,"Sat":20,"Sun":25,"Workday":19,"7 Day":20,"Count":604},"07-19":{"Mon":5932,"Tue":6111,"Wed":6278,"Thu":4646,"Fri":5198,"Sat":5351,"Sun":6125,"Workday":5564,"7 Day":5611,"Count":170943},"06-22":{"Mon":7327,"Tue":7476,"Wed":7738,"Thu":5634,"Fri":6362,"Sat":6450,"Sun":7703,"Workday":6821,"7 Day":6892,"Count":209474},"06-24":{"Mon":7600,"Tue":7758,"Wed":8048,"Thu":5854,"Fri":6617,"Sat":6718,"Sun":8127,"Workday":7086,"7 Day":7180,"Count":218081},"00-24":{"Mon":8129,"Tue":8251,"Wed":8586,"Thu":6238,"Fri":7019,"Sat":7056,"Sun":8470,"Workday":7548,"7 Day":7607,"Count":231304},"am Peak":{"Mon":"06:30:00","Tue":"08:45:00","Wed":"08:15:00","Thu":"09:00:00","Fri":"08:30:00","Sat":"11:00:00","Sun":"11:00:00","Workday":"08:45:00","7 Day":"09:15:00","Count":""},"Peak Volume":{"Mon":132,"Tue":135,"Wed":140,"Thu":100,"Fri":143,"Sat":138,"Sun":167,"Workday":127,"7 Day":134,"Count":null},"pm Peak":{"Mon":"16:30:00","Tue":"16:30:00","Wed":"16:15:00","Thu":"16:30:00","Fri":"15:45:00","Sat":"16:00:00","Sun":"15:45:00","Workday":"16:15:00","7 Day":"16:00:00","Count":""}},"Eastbound 2":{"00:00:00":{"Mon":2,"Tue":3,"Wed":1,"Thu":2,"Fri":2,"Sat":4,"Sun":4,"Workday":2,"7 Day":3,"Count":78},"00:15:00":{"Mon":2,"Tue":4,"Wed":3,"Thu":2,"Fri":1,"Sat":3,"Sun":4,"Workday":2,"7 Day":3,"Count":80},"00:30:00":{"Mon":0,"Tue":1,"Wed":1,"Thu":1,"Fri":1,"Sat":2,"Sun":2,"Workday":1,"7 Day":1,"Count":35},"00:45:00":{"Mon":2,"Tue":2,"Wed":1,"Thu":1,"Fri":1,"Sat":2,"Sun":2,"Workday":1,"7 Day":1,"Count":45},"01:00:00":{"Mon":1,"Tue":1,"Wed":1,"Thu":0,"Fri":1,"Sat":2,"Sun":1,"Workday":1,"7 Day":1,"Count":36},"01:15:00":{"Mon":0,"Tue":0,"Wed":0,"Thu":1,"Fri":0,"Sat":1,"Sun":1,"Workday":0,"7 Day":1,"Count":21},"01:30:00":{"Mon":0,"Tue":0,"Wed":0,"Thu":1,"Fri":0,"Sat":0,"Sun":0,"Workday":1,"7 Day":1,"Count":16},"01:45:00":{"Mon":1,"Tue":0,"Wed":1,"Thu":1,"Fri":1,"Sat":0,"Sun":0,"Workday":1,"7 Day":1,"Count":22},"02:00:00":{"Mon":0,"Tue":0,"Wed":1,"Thu":0,"Fri":0,"Sat":0,"Sun":1,"Workday":0,"7 Day":0,"Count":14},"02:15:00":{"Mon":0,"Tue":1,"Wed":0,"Thu":0,"Fri":1,"Sat":1,"Sun":1,"Workday":1,"7 Day":1,"Count":20},"02:30:00":{"Mon":0,"Tue":0,"Wed":1,"Thu":0,"Fri":0,"Sat":0,"Sun":1,"Workday":0,"7 Day":0,"Count":13},"02:45:00":{"Mon":1,"Tue":0,"Wed":0,"Thu":1,"Fri":1,"Sat":0,"Sun":1,"Workday":1,"7 Day":1,"Count":16},"03:00:00":{"Mon":0,"Tue":1,"Wed":2,"Thu":0,"Fri":0,"Sat":0,"Sun":2,"Workday":1,"7 Day":1,"Count":22},"03:15:00":{"Mon":1,"Tue":0,"Wed":0,"Thu":1,"Fri":1,"Sat":1,"Sun":1,"Workday":1,"7 Day":1,"Count":23},"03:30:00":{"Mon":1,"Tue":2,"Wed":3,"Thu":2,"Fri":1,"Sat":1,"Sun":1,"Workday":2,"7 Day":1,"Count":46},"03:45:00":{"Mon":1,"Tue":2,"Wed":3,"Thu":1,"Fri":1,"Sat":0,"Sun":1,"Workday":2,"7 Day":1,"Count":40},"04:00:00":{"Mon":1,"Tue":2,"Wed":2,"Thu":1,"Fri":3,"Sat":1,"Sun":1,"Workday":2,"7 Day":1,"Count":46},"04:15:00":{"Mon":4,"Tue":2,"Wed":3,"Thu":2,"Fri":2,"Sat":1,"Sun":1,"Workday":2,"7 Day":2,"Count":59},"04:30:00":{"Mon":5,"Tue":8,"Wed":6,"Thu":2,"Fri":4,"Sat":1,"Sun":2,"Workday":5,"7 Day":4,"Count":120},"04:45:00":{"Mon":6,"Tue":9,"Wed":7,"Thu":3,"Fri":4,"Sat":3,"Sun":0,"Workday":6,"7 Day":5,"Count":142},"05:00:00":{"Mon":13,"Tue":8,"Wed":8,"Thu":5,"Fri":8,"Sat":3,"Sun":1,"Workday":8,"7 Day":7,"Count":202},"05:15:00":{"Mon":16,"Tue":13,"Wed":12,"Thu":5,"Fri":9,"Sat":3,"Sun":1,"Workday":11,"7 Day":8,"Count":250},"05:30:00":{"Mon":28,"Tue":32,"Wed":29,"Thu":17,"Fri":19,"Sat":4,"Sun":2,"Workday":24,"7 Day":18,"Count":563},"05:45:00":{"Mon":53,"Tue":38,"Wed":47,"Thu":22,"Fri":25,"Sat":4,"Sun":2,"Workday":36,"7 Day":26,"Count":815},"06:00:00":{"Mon":103,"Tue":92,"Wed":106,"Thu":54,"Fri":62,"Sat":9,"Sun":4,"Workday":81,"7 Day":60,"Count":1844},"06:15:00":{"Mon":215,"Tue":194,"Wed":194,"Thu":114,"Fri":105,"Sat":15,"Sun":8,"Workday":159,"7 Day":117,"Count":3607},"06:30:00":{"Mon":278,"Tue":257,"Wed":232,"Thu":131,"Fri":133,"Sat":18,"Sun":7,"Workday":200,"7 Day":146,"Count":4506},"06:45:00":{"Mon":270,"Tue":224,"Wed":236,"Thu":128,"Fri":137,"Sat":18,"Sun":9,"Workday":193,"7 Day":142,"Count":4376},"07:00:00":{"Mon":248,"Tue":218,"Wed":212,"Thu":117,"Fri":125,"Sat":22,"Sun":6,"Workday":178,"7 Day":132,"Count":4055},"07:15:00":{"Mon":222,"Tue":202,"Wed":212,"Thu":108,"Fri":137,"Sat":30,"Sun":7,"Workday":171,"7 Day":128,"Count":3950},"07:30:00":{"Mon":157,"Tue":161,"Wed":189,"Thu":105,"Fri":138,"Sat":31,"Sun":11,"Workday":147,"7 Day":112,"Count":3439},"07:45:00":{"Mon":120,"Tue":153,"Wed":170,"Thu":98,"Fri":112,"Sat":23,"Sun":8,"Workday":128,"7 Day":96,"Count":2969},"08:00:00":{"Mon":132,"Tue":158,"Wed":200,"Thu":97,"Fri":112,"Sat":31,"Sun":10,"Workday":137,"7 Day":104,"Count":3202},"08:15:00":{"Mon":162,"Tue":168,"Wed":199,"Thu":108,"Fri":108,"Sat":50,"Sun":14,"Workday":145,"7 Day":113,"Count":3500},"08:30:00":{"Mon":132,"Tue":171,"Wed":175,"Thu":111,"Fri":110,"Sat":52,"Sun":14,"Workday":137,"7 Day":108,"Count":3333},"08:45:00":{"Mon":166,"Tue":162,"Wed":177,"Thu":102,"Fri":122,"Sat":54,"Sun":16,"Workday":143,"7 Day":113,"Count":3473},"09:00:00":{"Mon":134,"Tue":178,"Wed":168,"Thu":102,"Fri":104,"Sat":52,"Sun":24,"Workday":134,"7 Day":107,"Count":3308},"09:15:00":{"Mon":127,"Tue":193,"Wed":163,"Thu":101,"Fri":111,"Sat":56,"Sun":25,"Workday":136,"7 Day":109,"Count":3368},"09:30:00":{"Mon":149,"Tue":159,"Wed":155,"Thu":94,"Fri":102,"Sat":73,"Sun":32,"Workday":129,"7 Day":108,"Count":3326},"09:45:00":{"Mon":146,"Tue":137,"Wed":118,"Thu":82,"Fri":85,"Sat":83,"Sun":30,"Workday":111,"7 Day":96,"Count":2970},"10:00:00":{"Mon":160,"Tue":109,"Wed":107,"Thu":72,"Fri":79,"Sat":85,"Sun":41,"Workday":103,"7 Day":92,"Count":2848},"10:15:00":{"Mon":112,"Tue":105,"Wed":98,"Thu":82,"Fri":67,"Sat":84,"Sun":48,"Workday":91,"7 Day":84,"Count":2615},"10:30:00":{"Mon":97,"Tue":93,"Wed":85,"Thu":80,"Fri":66,"Sat":104,"Sun":49,"Workday":83,"7 Day":82,"Count":2546},"10:45:00":{"Mon":94,"Tue":84,"Wed":83,"Thu":70,"Fri":70,"Sat":102,"Sun":55,"Workday":79,"7 Day":80,"Count":2471},"11:00:00":{"Mon":86,"Tue":68,"Wed":84,"Thu":75,"Fri":76,"Sat":99,"Sun":52,"Workday":78,"7 Day":78,"Count":2415},"11:15:00":{"Mon":90,"Tue":90,"Wed":84,"Thu":70,"Fri":75,"Sat":105,"Sun":71,"Workday":81,"7 Day":84,"Count":2590},"11:30:00":{"Mon":94,"Tue":80,"Wed":89,"Thu":81,"Fri":70,"Sat":107,"Sun":96,"Workday":82,"7 Day":88,"Count":2734},"11:45:00":{"Mon":75,"Tue":74,"Wed":87,"Thu":69,"Fri":82,"Sat":122,"Sun":93,"Workday":77,"7 Day":86,"Count":2677},"12:00:00":{"Mon":83,"Tue":76,"Wed":95,"Thu":66,"Fri":78,"Sat":110,"Sun":102,"Workday":79,"7 Day":87,"Count":2694},"12:15:00":{"Mon":82,"Tue":82,"Wed":91,"Thu":68,"Fri":89,"Sat":111,"Sun":117,"Workday":82,"7 Day":91,"Count":2835},"12:30:00":{"Mon":87,"Tue":85,"Wed":111,"Thu":77,"Fri":95,"Sat":132,"Sun":127,"Workday":90,"7 Day":102,"Count":3157},"12:45:00":{"Mon":91,"Tue":88,"Wed":103,"Thu":84,"Fri":96,"Sat":122,"Sun":144,"Workday":92,"7 Day":104,"Count":3221},"13:00:00":{"Mon":91,"Tue":79,"Wed":105,"Thu":71,"Fri":92,"Sat":133,"Sun":145,"Workday":87,"7 Day":102,"Count":3163},"13:15:00":{"Mon":94,"Tue":110,"Wed":112,"Thu":82,"Fri":101,"Sat":109,"Sun":147,"Workday":99,"7 Day":107,"Count":3311},"13:30:00":{"Mon":105,"Tue":102,"Wed":95,"Thu":71,"Fri":98,"Sat":119,"Sun":161,"Workday":94,"7 Day":106,"Count":3298},"13:45:00":{"Mon":98,"Tue":96,"Wed":100,"Thu":81,"Fri":102,"Sat":118,"Sun":154,"Workday":95,"7 Day":106,"Count":3299},"14:00:00":{"Mon":116,"Tue":100,"Wed":113,"Thu":76,"Fri":103,"Sat":121,"Sun":155,"Workday":101,"7 Day":111,"Count":3439},"14:15:00":{"Mon":98,"Tue":111,"Wed":119,"Thu":81,"Fri":106,"Sat":111,"Sun":156,"Workday":102,"7 Day":110,"Count":3429},"14:30:00":{"Mon":103,"Tue":93,"Wed":121,"Thu":76,"Fri":126,"Sat":100,"Sun":149,"Workday":104,"7 Day":109,"Count":3378},"14:45:00":{"Mon":88,"Tue":101,"Wed":120,"Thu":78,"Fri":125,"Sat":98,"Sun":155,"Workday":102,"7 Day":108,"Count":3357},"15:00:00":{"Mon":108,"Tue":97,"Wed":120,"Thu":87,"Fri":128,"Sat":74,"Sun":142,"Workday":108,"7 Day":108,"Count":3237},"15:15:00":{"Mon":113,"Tue":104,"Wed":128,"Thu":78,"Fri":122,"Sat":85,"Sun":152,"Workday":108,"7 Day":111,"Count":3332},"15:30:00":{"Mon":113,"Tue":109,"Wed":130,"Thu":87,"Fri":113,"Sat":84,"Sun":158,"Workday":110,"7 Day":113,"Count":3382},"15:45:00":{"Mon":114,"Tue":127,"Wed":136,"Thu":85,"Fri":165,"Sat":116,"Sun":162,"Workday":123,"7 Day":128,"Count":3706},"16:00:00":{"Mon":129,"Tue":128,"Wed":142,"Thu":86,"Fri":155,"Sat":104,"Sun":185,"Workday":126,"7 Day":131,"Count":3802},"16:15:00":{"Mon":117,"Tue":123,"Wed":156,"Thu":89,"Fri":168,"Sat":114,"Sun":204,"Workday":129,"7 Day":137,"Count":3973},"16:30:00":{"Mon":135,"Tue":141,"Wed":144,"Thu":84,"Fri":152,"Sat":106,"Sun":179,"Workday":129,"7 Day":133,"Count":3849},"16:45:00":{"Mon":121,"Tue":136,"Wed":154,"Thu":94,"Fri":160,"Sat":117,"Sun":198,"Workday":131,"7 Day":139,"Count":4013},"17:00:00":{"Mon":107,"Tue":142,"Wed":146,"Thu":92,"Fri":142,"Sat":121,"Sun":180,"Workday":124,"7 Day":132,"Count":3810},"17:15:00":{"Mon":116,"Tue":138,"Wed":144,"Thu":87,"Fri":115,"Sat":112,"Sun":202,"Workday":119,"7 Day":129,"Count":3863},"17:30:00":{"Mon":108,"Tue":139,"Wed":146,"Thu":89,"Fri":113,"Sat":107,"Sun":205,"Workday":118,"7 Day":128,"Count":3833},"17:45:00":{"Mon":105,"Tue":114,"Wed":141,"Thu":85,"Fri":109,"Sat":89,"Sun":200,"Workday":110,"7 Day":120,"Count":3568},"18:00:00":{"Mon":108,"Tue":122,"Wed":144,"Thu":87,"Fri":115,"Sat":98,"Sun":210,"Workday":114,"7 Day":126,"Count":3744},"18:15:00":{"Mon":80,"Tue":115,"Wed":132,"Thu":75,"Fri":112,"Sat":91,"Sun":204,"Workday":102,"7 Day":115,"Count":3419},"18:30:00":{"Mon":94,"Tue":102,"Wed":110,"Thu":80,"Fri":101,"Sat":87,"Sun":187,"Workday":97,"7 Day":108,"Count":3223},"18:45:00":{"Mon":91,"Tue":86,"Wed":119,"Thu":70,"Fri":93,"Sat":83,"Sun":191,"Workday":91,"7 Day":104,"Count":3094},"19:00:00":{"Mon":82,"Tue":84,"Wed":106,"Thu":57,"Fri":85,"Sat":69,"Sun":181,"Workday":82,"7 Day":94,"Count":2801},"19:15:00":{"Mon":66,"Tue":76,"Wed":101,"Thu":59,"Fri":75,"Sat":62,"Sun":196,"Workday":74,"7 Day":90,"Count":2668},"19:30:00":{"Mon":57,"Tue":56,"Wed":80,"Thu":42,"Fri":63,"Sat":54,"Sun":164,"Workday":59,"7 Day":73,"Count":2170},"19:45:00":{"Mon":44,"Tue":47,"Wed":60,"Thu":37,"Fri":51,"Sat":45,"Sun":163,"Workday":48,"7 Day":64,"Count":1882},"20:00:00":{"Mon":39,"Tue":45,"Wed":55,"Thu":43,"Fri":53,"Sat":52,"Sun":147,"Workday":47,"7 Day":62,"Count":1828},"20:15:00":{"Mon":34,"Tue":39,"Wed":48,"Thu":32,"Fri":46,"Sat":46,"Sun":140,"Workday":40,"7 Day":55,"Count":1623},"20:30:00":{"Mon":34,"Tue":35,"Wed":44,"Thu":30,"Fri":42,"Sat":35,"Sun":133,"Workday":37,"7 Day":50,"Count":1482},"20:45:00":{"Mon":34,"Tue":36,"Wed":35,"Thu":24,"Fri":33,"Sat":23,"Sun":109,"Workday":32,"7 Day":42,"Count":1235},"21:00:00":{"Mon":28,"Tue":28,"Wed":35,"Thu":20,"Fri":26,"Sat":24,"Sun":104,"Workday":27,"7 Day":38,"Count":1107},"21:15:00":{"Mon":32,"Tue":25,"Wed":36,"Thu":17,"Fri":24,"Sat":24,"Sun":84,"Workday":26,"7 Day":34,"Count":1009},"21:30:00":{"Mon":24,"Tue":27,"Wed":32,"Thu":13,"Fri":15,"Sat":15,"Sun":72,"Workday":22,"7 Day":28,"Count":824},"21:45:00":{"Mon":21,"Tue":25,"Wed":28,"Thu":12,"Fri":19,"Sat":18,"Sun":51,"Workday":20,"7 Day":24,"Count":726},"22:00:00":{"Mon":16,"Tue":21,"Wed":21,"Thu":11,"Fri":17,"Sat":11,"Sun":44,"Workday":17,"7 Day":20,"Count":594},"22:15:00":{"Mon":15,"Tue":17,"Wed":16,"Thu":7,"Fri":11,"Sat":10,"Sun":35,"Workday":13,"7 Day":16,"Count":466},"22:30:00":{"Mon":10,"Tue":16,"Wed":13,"Thu":10,"Fri":14,"Sat":7,"Sun":30,"Workday":12,"7 Day":14,"Count":423},"22:45:00":{"Mon":9,"Tue":9,"Wed":12,"Thu":9,"Fri":7,"Sat":7,"Sun":18,"Workday":9,"7 Day":10,"Count":303},"23:00:00":{"Mon":7,"Tue":10,"Wed":9,"Thu":5,"Fri":6,"Sat":6,"Sun":16,"Workday":8,"7 Day":8,"Count":253},"23:15:00":{"Mon":3,"Tue":6,"Wed":6,"Thu":3,"Fri":6,"Sat":5,"Sun":9,"Workday":5,"7 Day":6,"Count":167},"23:30:00":{"Mon":4,"Tue":3,"Wed":4,"Thu":3,"Fri":4,"Sat":4,"Sun":5,"Workday":4,"7 Day":4,"Count":121},"23:45:00":{"Mon":3,"Tue":3,"Wed":4,"Thu":2,"Fri":2,"Sat":4,"Sun":4,"Workday":3,"7 Day":3,"Count":90},"07-19":{"Mon":5600,"Tue":5817,"Wed":6333,"Thu":4091,"Fri":5224,"Sat":4336,"Sun":5372,"Workday":5336,"7 Day":5204,"Count":158218},"06-22":{"Mon":6962,"Tue":7107,"Wed":7762,"Thu":4905,"Fri":6194,"Sat":4862,"Sun":6945,"Workday":6483,"7 Day":6323,"Count":191906},"06-24":{"Mon":7030,"Tue":7193,"Wed":7848,"Thu":4955,"Fri":6262,"Sat":4915,"Sun":7106,"Workday":6554,"7 Day":6405,"Count":194323},"00-24":{"Mon":7169,"Tue":7322,"Wed":7980,"Thu":5028,"Fri":6350,"Sat":4953,"Sun":7139,"Workday":6664,"7 Day":6493,"Count":197047},"am Peak":{"Mon":"06:30:00","Tue":"06:30:00","Wed":"06:30:00","Thu":"06:15:00","Fri":"06:45:00","Sat":"11:00:00","Sun":"11:00:00","Workday":"06:30:00","7 Day":"06:30:00","Count":""},"Peak Volume":{"Mon":126,"Tue":139,"Wed":150,"Thu":90,"Fri":160,"Sat":125,"Sun":205,"Workday":129,"7 Day":135,"Count":null},"pm Peak":{"Mon":"16:00:00","Tue":"16:30:00","Wed":"16:15:00","Thu":"16:45:00","Fri":"15:45:00","Sat":"12:15:00","Sun":"17:30:00","Workday":"16:00:00","7 Day":"16:15:00","Count":""}},"Westbound 2":{"00:00:00":{"Mon":11,"Tue":5,"Wed":9,"Thu":5,"Fri":4,"Sat":12,"Sun":14,"Workday":6,"7 Day":8,"Count":262},"00:15:00":{"Mon":7,"Tue":6,"Wed":9,"Thu":7,"Fri":9,"Sat":12,"Sun":8,"Workday":8,"7 Day":9,"Count":265},"00:30:00":{"Mon":7,"Tue":6,"Wed":7,"Thu":6,"Fri":6,"Sat":10,"Sun":9,"Workday":6,"7 Day":7,"Count":224},"00:45:00":{"Mon":5,"Tue":5,"Wed":4,"Thu":6,"Fri":6,"Sat":9,"Sun":10,"Workday":5,"7 Day":6,"Count":202},"01:00:00":{"Mon":4,"Tue":4,"Wed":4,"Thu":4,"Fri":5,"Sat":10,"Sun":5,"Workday":4,"7 Day":5,"Count":165},"01:15:00":{"Mon":3,"Tue":3,"Wed":4,"Thu":4,"Fri":4,"Sat":5,"Sun":5,"Workday":4,"7 Day":4,"Count":133},"01:30:00":{"Mon":5,"Tue":5,"Wed":4,"Thu":2,"Fri":3,"Sat":6,"Sun":4,"Workday":4,"7 Day":4,"Count":127},"01:45:00":{"Mon":2,"Tue":2,"Wed":2,"Thu":4,"Fri":2,"Sat":6,"Sun":3,"Workday":2,"7 Day":3,"Count":95},"02:00:00":{"Mon":2,"Tue":2,"Wed":4,"Thu":2,"Fri":1,"Sat":2,"Sun":4,"Workday":2,"7 Day":2,"Count":74},"02:15:00":{"Mon":2,"Tue":2,"Wed":1,"Thu":1,"Fri":3,"Sat":3,"Sun":3,"Workday":2,"7 Day":2,"Count":64},"02:30:00":{"Mon":0,"Tue":2,"Wed":1,"Thu":2,"Fri":1,"Sat":2,"Sun":2,"Workday":1,"7 Day":2,"Count":48},"02:45:00":{"Mon":0,"Tue":2,"Wed":2,"Thu":1,"Fri":1,"Sat":2,"Sun":2,"Workday":1,"7 Day":2,"Count":49},"03:00:00":{"Mon":2,"Tue":0,"Wed":1,"Thu":2,"Fri":2,"Sat":2,"Sun":1,"Workday":1,"7 Day":1,"Count":45},"03:15:00":{"Mon":2,"Tue":1,"Wed":2,"Thu":1,"Fri":1,"Sat":1,"Sun":1,"Workday":1,"7 Day":1,"Count":40},"03:30:00":{"Mon":2,"Tue":2,"Wed":2,"Thu":1,"Fri":1,"Sat":2,"Sun":1,"Workday":1,"7 Day":1,"Count":44},"03:45:00":{"Mon":1,"Tue":0,"Wed":2,"Thu":1,"Fri":2,"Sat":1,"Sun":0,"Workday":1,"7 Day":1,"Count":33},"04:00:00":{"Mon":1,"Tue":0,"Wed":1,"Thu":1,"Fri":2,"Sat":2,"Sun":2,"Workday":1,"7 Day":1,"Count":40},"04:15:00":{"Mon":2,"Tue":2,"Wed":0,"Thu":1,"Fri":3,"Sat":2,"Sun":1,"Workday":2,"7 Day":2,"Count":53},"04:30:00":{"Mon":4,"Tue":3,"Wed":2,"Thu":1,"Fri":2,"Sat":1,"Sun":2,"Workday":3,"7 Day":2,"Count":71},"04:45:00":{"Mon":2,"Tue":2,"Wed":4,"Thu":3,"Fri":3,"Sat":2,"Sun":1,"Workday":3,"7 Day":2,"Count":74},"05:00:00":{"Mon":5,"Tue":3,"Wed":2,"Thu":3,"Fri":2,"Sat":3,"Sun":1,"Workday":3,"7 Day":3,"Count":87},"05:15:00":{"Mon":8,"Tue":4,"Wed":6,"Thu":4,"Fri":3,"Sat":3,"Sun":1,"Workday":5,"7 Day":4,"Count":132},"05:30:00":{"Mon":12,"Tue":6,"Wed":9,"Thu":6,"Fri":6,"Sat":3,"Sun":1,"Workday":8,"7 Day":6,"Count":187},"05:45:00":{"Mon":15,"Tue":9,"Wed":10,"Thu":8,"Fri":8,"Sat":5,"Sun":2,"Workday":10,"7 Day":8,"Count":250},"06:00:00":{"Mon":17,"Tue":12,"Wed":14,"Thu":6,"Fri":8,"Sat":3,"Sun":3,"Workday":11,"7 Day":9,"Count":278},"06:15:00":{"Mon":32,"Tue":20,"Wed":24,"Thu":20,"Fri":12,"Sat":2,"Sun":3,"Workday":21,"7 Day":16,"Count":488},"06:30:00":{"Mon":40,"Tue":34,"Wed":38,"Thu":20,"Fri":20,"Sat":9,"Sun":3,"Workday":29,"7 Day":23,"Count":702},"06:45:00":{"Mon":59,"Tue":47,"Wed":38,"Thu":23,"Fri":24,"Sat":11,"Sun":6,"Workday":37,"7 Day":29,"Count":889},"07:00:00":{"Mon":79,"Tue":62,"Wed":52,"Thu":38,"Fri":30,"Sat":14,"Sun":6,"Workday":51,"7 Day":39,"Count":1206},"07:15:00":{"Mon":97,"Tue":86,"Wed":80,"Thu":50,"Fri":44,"Sat":16,"Sun":9,"Workday":69,"7 Day":53,"Count":1635},"07:30:00":{"Mon":101,"Tue":93,"Wed":104,"Thu":56,"Fri":49,"Sat":21,"Sun":7,"Workday":78,"7 Day":60,"Count":1851},"07:45:00":{"Mon":97,"Tue":98,"Wed":105,"Thu":62,"Fri":59,"Sat":20,"Sun":10,"Workday":82,"7 Day":63,"Count":1949},"08:00:00":{"Mon":108,"Tue":111,"Wed":110,"Thu":65,"Fri":68,"Sat":23,"Sun":10,"Workday":90,"7 Day":69,"Count":2133},"08:15:00":{"Mon":132,"Tue":142,"Wed":137,"Thu":72,"Fri":82,"Sat":29,"Sun":13,"Workday":110,"7 Day":85,"Count":2610},"08:30:00":{"Mon":136,"Tue":161,"Wed":142,"Thu":87,"Fri":90,"Sat":36,"Sun":19,"Workday":120,"7 Day":94,"Count":2899},"08:45:00":{"Mon":124,"Tue":123,"Wed":134,"Thu":72,"Fri":79,"Sat":39,"Sun":22,"Workday":104,"7 Day":83,"Count":2565},"09:00:00":{"Mon":99,"Tue":103,"Wed":94,"Thu":62,"Fri":63,"Sat":42,"Sun":19,"Workday":82,"7 Day":68,"Count":2100},"09:15:00":{"Mon":96,"Tue":96,"Wed":95,"Thu":64,"Fri":60,"Sat":50,"Sun":22,"Workday":81,"7 Day":68,"Count":2110},"09:30:00":{"Mon":109,"Tue":92,"Wed":102,"Thu":66,"Fri":60,"Sat":70,"Sun":24,"Workday":84,"7 Day":74,"Count":2291},"09:45:00":{"Mon":90,"Tue":84,"Wed":83,"Thu":58,"Fri":67,"Sat":70,"Sun":37,"Workday":75,"7 Day":69,"Count":2148},"10:00:00":{"Mon":88,"Tue":86,"Wed":84,"Thu":67,"Fri":69,"Sat":84,"Sun":39,"Workday":78,"7 Day":74,"Count":2289},"10:15:00":{"Mon":85,"Tue":82,"Wed":69,"Thu":62,"Fri":86,"Sat":77,"Sun":46,"Workday":77,"7 Day":73,"Count":2256},"10:30:00":{"Mon":75,"Tue":77,"Wed":79,"Thu":70,"Fri":81,"Sat":86,"Sun":66,"Workday":76,"7 Day":76,"Count":2371},"10:45:00":{"Mon":67,"Tue":72,"Wed":77,"Thu":72,"Fri":76,"Sat":102,"Sun":66,"Workday":73,"7 Day":77,"Count":2380},"11:00:00":{"Mon":78,"Tue":69,"Wed":70,"Thu":56,"Fri":87,"Sat":92,"Sun":72,"Workday":72,"7 Day":75,"Count":2335},"11:15:00":{"Mon":80,"Tue":80,"Wed":75,"Thu":72,"Fri":85,"Sat":110,"Sun":73,"Workday":78,"7 Day":83,"Count":2563},"11:30:00":{"Mon":78,"Tue":77,"Wed":81,"Thu":77,"Fri":93,"Sat":120,"Sun":98,"Workday":81,"7 Day":90,"Count":2783},"11:45:00":{"Mon":76,"Tue":82,"Wed":83,"Thu":74,"Fri":104,"Sat":126,"Sun":92,"Workday":84,"7 Day":92,"Count":2855},"12:00:00":{"Mon":78,"Tue":75,"Wed":88,"Thu":68,"Fri":104,"Sat":131,"Sun":104,"Workday":83,"7 Day":93,"Count":2897},"12:15:00":{"Mon":88,"Tue":94,"Wed":98,"Thu":71,"Fri":112,"Sat":129,"Sun":122,"Workday":92,"7 Day":102,"Count":3170},"12:30:00":{"Mon":87,"Tue":105,"Wed":106,"Thu":86,"Fri":107,"Sat":142,"Sun":127,"Workday":98,"7 Day":109,"Count":3379},"12:45:00":{"Mon":84,"Tue":86,"Wed":104,"Thu":86,"Fri":131,"Sat":126,"Sun":134,"Workday":99,"7 Day":108,"Count":3343},"13:00:00":{"Mon":100,"Tue":83,"Wed":111,"Thu":77,"Fri":129,"Sat":122,"Sun":133,"Workday":100,"7 Day":108,"Count":3346},"13:15:00":{"Mon":93,"Tue":95,"Wed":117,"Thu":95,"Fri":142,"Sat":150,"Sun":141,"Workday":109,"7 Day":120,"Count":3724},"13:30:00":{"Mon":110,"Tue":96,"Wed":109,"Thu":78,"Fri":142,"Sat":123,"Sun":136,"Workday":107,"7 Day":114,"Count":3522},"13:45:00":{"Mon":99,"Tue":101,"Wed":118,"Thu":87,"Fri":147,"Sat":139,"Sun":134,"Workday":111,"7 Day":118,"Count":3674},"14:00:00":{"Mon":105,"Tue":96,"Wed":113,"Thu":89,"Fri":161,"Sat":126,"Sun":137,"Workday":114,"7 Day":119,"Count":3687},"14:15:00":{"Mon":105,"Tue":110,"Wed":131,"Thu":88,"Fri":159,"Sat":126,"Sun":128,"Workday":119,"7 Day":121,"Count":3764},"14:30:00":{"Mon":118,"Tue":110,"Wed":126,"Thu":100,"Fri":167,"Sat":125,"Sun":126,"Workday":125,"7 Day":125,"Count":3881},"14:45:00":{"Mon":123,"Tue":113,"Wed":142,"Thu":94,"Fri":167,"Sat":123,"Sun":124,"Workday":128,"7 Day":127,"Count":3927},"15:00:00":{"Mon":109,"Tue":124,"Wed":151,"Thu":97,"Fri":222,"Sat":97,"Sun":115,"Workday":142,"7 Day":132,"Count":3980},"15:15:00":{"Mon":133,"Tue":144,"Wed":163,"Thu":105,"Fri":210,"Sat":108,"Sun":127,"Workday":152,"7 Day":142,"Count":4281},"15:30:00":{"Mon":156,"Tue":157,"Wed":194,"Thu":121,"Fri":194,"Sat":101,"Sun":133,"Workday":164,"7 Day":151,"Count":4543},"15:45:00":{"Mon":163,"Tue":170,"Wed":204,"Thu":133,"Fri":256,"Sat":137,"Sun":129,"Workday":183,"7 Day":169,"Count":4904},"16:00:00":{"Mon":187,"Tue":186,"Wed":224,"Thu":126,"Fri":258,"Sat":128,"Sun":124,"Workday":193,"7 Day":174,"Count":5060},"16:15:00":{"Mon":208,"Tue":219,"Wed":249,"Thu":144,"Fri":270,"Sat":151,"Sun":132,"Workday":215,"7 Day":194,"Count":5639},"16:30:00":{"Mon":218,"Tue":252,"Wed":265,"Thu":158,"Fri":251,"Sat":128,"Sun":138,"Workday":225,"7 Day":199,"Count":5796},"16:45:00":{"Mon":250,"Tue":268,"Wed":288,"Thu":164,"Fri":267,"Sat":144,"Sun":136,"Workday":244,"7 Day":214,"Count":6235},"17:00:00":{"Mon":246,"Tue":274,"Wed":277,"Thu":166,"Fri":235,"Sat":152,"Sun":128,"Workday":236,"7 Day":209,"Count":6076},"17:15:00":{"Mon":262,"Tue":280,"Wed":249,"Thu":164,"Fri":215,"Sat":155,"Sun":147,"Workday":230,"7 Day":207,"Count":6270},"17:30:00":{"Mon":273,"Tue":288,"Wed":288,"Thu":171,"Fri":211,"Sat":124,"Sun":146,"Workday":241,"7 Day":211,"Count":6390},"17:45:00":{"Mon":265,"Tue":266,"Wed":278,"Thu":155,"Fri":204,"Sat":125,"Sun":137,"Workday":229,"7 Day":201,"Count":6076},"18:00:00":{"Mon":268,"Tue":268,"Wed":292,"Thu":170,"Fri":180,"Sat":124,"Sun":135,"Workday":230,"7 Day":201,"Count":6099},"18:15:00":{"Mon":272,"Tue":241,"Wed":274,"Thu":161,"Fri":174,"Sat":112,"Sun":124,"Workday":219,"7 Day":191,"Count":5773},"18:30:00":{"Mon":222,"Tue":194,"Wed":272,"Thu":136,"Fri":179,"Sat":99,"Sun":133,"Workday":197,"7 Day":174,"Count":5254},"18:45:00":{"Mon":200,"Tue":208,"Wed":259,"Thu":109,"Fri":175,"Sat":82,"Sun":130,"Workday":186,"7 Day":163,"Count":4931},"19:00:00":{"Mon":126,"Tue":165,"Wed":192,"Thu":106,"Fri":143,"Sat":82,"Sun":109,"Workday":144,"7 Day":130,"Count":3941},"19:15:00":{"Mon":119,"Tue":146,"Wed":197,"Thu":109,"Fri":143,"Sat":73,"Sun":108,"Workday":141,"7 Day":127,"Count":3832},"19:30:00":{"Mon":86,"Tue":102,"Wed":173,"Thu":86,"Fri":131,"Sat":68,"Sun":93,"Workday":115,"7 Day":105,"Count":3171},"19:45:00":{"Mon":79,"Tue":97,"Wed":119,"Thu":89,"Fri":112,"Sat":63,"Sun":91,"Workday":99,"7 Day":93,"Count":2800},"20:00:00":{"Mon":62,"Tue":80,"Wed":92,"Thu":105,"Fri":106,"Sat":58,"Sun":86,"Workday":90,"7 Day":85,"Count":2565},"20:15:00":{"Mon":61,"Tue":68,"Wed":98,"Thu":70,"Fri":91,"Sat":48,"Sun":78,"Workday":78,"7 Day":74,"Count":2214},"20:30:00":{"Mon":51,"Tue":58,"Wed":82,"Thu":52,"Fri":70,"Sat":44,"Sun":59,"Workday":62,"7 Day":59,"Count":1785},"20:45:00":{"Mon":44,"Tue":45,"Wed":65,"Thu":43,"Fri":61,"Sat":40,"Sun":57,"Workday":52,"7 Day":51,"Count":1520},"21:00:00":{"Mon":39,"Tue":51,"Wed":60,"Thu":39,"Fri":52,"Sat":30,"Sun":42,"Workday":48,"7 Day":44,"Count":1339},"21:15:00":{"Mon":33,"Tue":44,"Wed":54,"Thu":36,"Fri":46,"Sat":30,"Sun":34,"Workday":43,"7 Day":40,"Count":1195},"21:30:00":{"Mon":34,"Tue":47,"Wed":46,"Thu":37,"Fri":35,"Sat":27,"Sun":26,"Workday":39,"7 Day":36,"Count":1079},"21:45:00":{"Mon":27,"Tue":39,"Wed":38,"Thu":33,"Fri":28,"Sat":24,"Sun":27,"Workday":33,"7 Day":31,"Count":920},"22:00:00":{"Mon":28,"Tue":31,"Wed":42,"Thu":24,"Fri":21,"Sat":16,"Sun":23,"Workday":28,"7 Day":26,"Count":783},"22:15:00":{"Mon":27,"Tue":29,"Wed":34,"Thu":23,"Fri":26,"Sat":16,"Sun":16,"Workday":28,"7 Day":24,"Count":733},"22:30:00":{"Mon":18,"Tue":24,"Wed":28,"Thu":20,"Fri":28,"Sat":14,"Sun":14,"Workday":24,"7 Day":21,"Count":630},"22:45:00":{"Mon":14,"Tue":20,"Wed":24,"Thu":21,"Fri":29,"Sat":10,"Sun":15,"Workday":22,"7 Day":19,"Count":585},"23:00:00":{"Mon":10,"Tue":16,"Wed":26,"Thu":18,"Fri":27,"Sat":11,"Sun":12,"Workday":20,"7 Day":17,"Count":528},"23:15:00":{"Mon":13,"Tue":15,"Wed":24,"Thu":16,"Fri":20,"Sat":16,"Sun":13,"Workday":18,"7 Day":17,"Count":504},"23:30:00":{"Mon":10,"Tue":11,"Wed":13,"Thu":8,"Fri":15,"Sat":16,"Sun":9,"Workday":12,"7 Day":12,"Count":357},"23:45:00":{"Mon":7,"Tue":4,"Wed":9,"Thu":8,"Fri":13,"Sat":14,"Sun":7,"Workday":8,"7 Day":9,"Count":266},"07-19":{"Mon":6518,"Tue":6581,"Wed":7149,"Thu":4605,"Fri":6603,"Sat":4755,"Sun":4412,"Workday":6218,"7 Day":5759,"Count":174950},"06-22":{"Mon":7427,"Tue":7636,"Wed":8481,"Thu":5478,"Fri":7683,"Sat":5365,"Sun":5238,"Workday":7261,"7 Day":6709,"Count":203668},"06-24":{"Mon":7554,"Tue":7786,"Wed":8681,"Thu":5617,"Fri":7862,"Sat":5478,"Sun":5346,"Workday":7420,"7 Day":6854,"Count":208054},"00-24":{"Mon":7658,"Tue":7866,"Wed":8774,"Thu":5693,"Fri":7943,"Sat":5586,"Sun":5431,"Workday":7506,"7 Day":6943,"Count":210818},"am Peak":{"Mon":"08:00:00","Tue":"08:00:00","Wed":"08:00:00","Thu":"08:00:00","Fri":"11:00:00","Sat":"11:00:00","Sun":"11:00:00","Workday":"08:00:00","7 Day":"11:00:00","Count":""},"Peak Volume":{"Mon":269,"Tue":278,"Wed":283,"Thu":166,"Fri":262,"Sat":144,"Sun":141,"Workday":238,"7 Day":210,"Count":null},"pm Peak":{"Mon":"17:30:00","Tue":"16:45:00","Wed":"17:30:00","Thu":"16:45:00","Fri":"16:00:00","Sat":"16:30:00","Sun":"17:15:00","Workday":"16:45:00","7 Day":"16:45:00","Count":""}},"Westbound 1":{"00:00:00":{"Mon":30,"Tue":27,"Wed":32,"Thu":27,"Fri":23,"Sat":31,"Sun":34,"Workday":28,"7 Day":29,"Count":894},"00:15:00":{"Mon":29,"Tue":28,"Wed":30,"Thu":26,"Fri":26,"Sat":31,"Sun":34,"Workday":28,"7 Day":29,"Count":902},"00:30:00":{"Mon":27,"Tue":25,"Wed":27,"Thu":23,"Fri":24,"Sat":30,"Sun":35,"Workday":25,"7 Day":27,"Count":840},"00:45:00":{"Mon":21,"Tue":26,"Wed":24,"Thu":22,"Fri":23,"Sat":27,"Sun":34,"Workday":23,"7 Day":25,"Count":784},"01:00:00":{"Mon":22,"Tue":24,"Wed":26,"Thu":17,"Fri":22,"Sat":26,"Sun":26,"Workday":22,"7 Day":23,"Count":718},"01:15:00":{"Mon":18,"Tue":20,"Wed":21,"Thu":19,"Fri":18,"Sat":22,"Sun":26,"Workday":19,"7 Day":20,"Count":631},"01:30:00":{"Mon":16,"Tue":21,"Wed":19,"Thu":17,"Fri":16,"Sat":23,"Sun":18,"Workday":18,"7 Day":19,"Count":575},"01:45:00":{"Mon":14,"Tue":18,"Wed":18,"Thu":21,"Fri":17,"Sat":20,"Sun":22,"Workday":18,"7 Day":19,"Count":578},"02:00:00":{"Mon":15,"Tue":18,"Wed":17,"Thu":16,"Fri":16,"Sat":18,"Sun":20,"Workday":16,"7 Day":17,"Count":533},"02:15:00":{"Mon":10,"Tue":16,"Wed":19,"Thu":12,"Fri":17,"Sat":13,"Sun":20,"Workday":15,"7 Day":15,"Count":470},"02:30:00":{"Mon":12,"Tue":16,"Wed":20,"Thu":12,"Fri":13,"Sat":13,"Sun":18,"Workday":15,"7 Day":15,"Count":455},"02:45:00":{"Mon":10,"Tue":16,"Wed":18,"Thu":11,"Fri":12,"Sat":12,"Sun":12,"Workday":13,"7 Day":13,"Count":401},"03:00:00":{"Mon":12,"Tue":14,"Wed":16,"Thu":13,"Fri":14,"Sat":14,"Sun":13,"Workday":14,"7 Day":14,"Count":426},"03:15:00":{"Mon":9,"Tue":13,"Wed":16,"Thu":13,"Fri":10,"Sat":10,"Sun":11,"Workday":12,"7 Day":12,"Count":369},"03:30:00":{"Mon":9,"Tue":11,"Wed":14,"Thu":8,"Fri":13,"Sat":10,"Sun":10,"Workday":11,"7 Day":11,"Count":329},"03:45:00":{"Mon":7,"Tue":10,"Wed":12,"Thu":8,"Fri":10,"Sat":10,"Sun":10,"Workday":9,"7 Day":10,"Count":302},"04:00:00":{"Mon":12,"Tue":11,"Wed":14,"Thu":12,"Fri":11,"Sat":12,"Sun":9,"Workday":12,"7 Day":12,"Count":359},"04:15:00":{"Mon":14,"Tue":12,"Wed":11,"Thu":10,"Fri":11,"Sat":11,"Sun":10,"Workday":12,"7 Day":11,"Count":352},"04:30:00":{"Mon":15,"Tue":16,"Wed":18,"Thu":12,"Fri":15,"Sat":11,"Sun":11,"Workday":15,"7 Day":14,"Count":430},"04:45:00":{"Mon":18,"Tue":20,"Wed":21,"Thu":14,"Fri":15,"Sat":13,"Sun":10,"Workday":17,"7 Day":16,"Count":488},"05:00:00":{"Mon":20,"Tue":20,"Wed":23,"Thu":15,"Fri":18,"Sat":14,"Sun":11,"Workday":19,"7 Day":17,"Count":531},"05:15:00":{"Mon":27,"Tue":22,"Wed":26,"Thu":18,"Fri":20,"Sat":15,"Sun":11,"Workday":22,"7 Day":20,"Count":608},"05:30:00":{"Mon":40,"Tue":25,"Wed":30,"Thu":21,"Fri":22,"Sat":16,"Sun":11,"Workday":27,"7 Day":23,"Count":717},"05:45:00":{"Mon":39,"Tue":33,"Wed":33,"Thu":22,"Fri":27,"Sat":16,"Sun":15,"Workday":30,"7 Day":26,"Count":798},"06:00:00":{"Mon":42,"Tue":40,"Wed":40,"Thu":25,"Fri":31,"Sat":19,"Sun":17,"Workday":35,"7 Day":30,"Count":928},"06:15:00":{"Mon":60,"Tue":48,"Wed":50,"Thu":41,"Fri":40,"Sat":22,"Sun":19,"Workday":47,"7 Day":40,"Count":1226},"06:30:00":{"Mon":66,"Tue":66,"Wed":62,"Thu":46,"Fri":48,"Sat":30,"Sun":23,"Workday":57,"7 Day":48,"Count":1487},"06:45:00":{"Mon":89,"Tue":74,"Wed":78,"Thu":51,"Fri":57,"Sat":35,"Sun":26,"Workday":68,"7 Day":58,"Count":1788},"07:00:00":{"Mon":94,"Tue":94,"Wed":90,"Thu":57,"Fri":64,"Sat":38,"Sun":33,"Workday":78,"7 Day":66,"Count":2038},"07:15:00":{"Mon":100,"Tue":107,"Wed":96,"Thu":76,"Fri":72,"Sat":42,"Sun":44,"Workday":89,"7 Day":76,"Count":2338},"07:30:00":{"Mon":105,"Tue":118,"Wed":106,"Thu":76,"Fri":79,"Sat":51,"Sun":33,"Workday":95,"7 Day":80,"Count":2481},"07:45:00":{"Mon":110,"Tue":112,"Wed":117,"Thu":80,"Fri":85,"Sat":56,"Sun":44,"Workday":99,"7 Day":85,"Count":2638},"08:00:00":{"Mon":119,"Tue":116,"Wed":112,"Thu":78,"Fri":82,"Sat":59,"Sun":46,"Workday":99,"7 Day":86,"Count":2667},"08:15:00":{"Mon":127,"Tue":137,"Wed":134,"Thu":87,"Fri":97,"Sat":62,"Sun":51,"Workday":114,"7 Day":98,"Count":3028},"08:30:00":{"Mon":137,"Tue":129,"Wed":127,"Thu":95,"Fri":95,"Sat":71,"Sun":64,"Workday":115,"7 Day":101,"Count":3136},"08:45:00":{"Mon":119,"Tue":130,"Wed":122,"Thu":90,"Fri":89,"Sat":76,"Sun":65,"Workday":108,"7 Day":98,"Count":3020},"09:00:00":{"Mon":112,"Tue":114,"Wed":114,"Thu":84,"Fri":86,"Sat":82,"Sun":63,"Workday":101,"7 Day":93,"Count":2874},"09:15:00":{"Mon":112,"Tue":115,"Wed":109,"Thu":89,"Fri":84,"Sat":86,"Sun":64,"Workday":101,"7 Day":94,"Count":2900},"09:30:00":{"Mon":118,"Tue":116,"Wed":113,"Thu":92,"Fri":85,"Sat":96,"Sun":79,"Workday":103,"7 Day":99,"Count":3067},"09:45:00":{"Mon":106,"Tue":117,"Wed":112,"Thu":90,"Fri":90,"Sat":104,"Sun":90,"Workday":102,"7 Day":101,"Count":3117},"10:00:00":{"Mon":109,"Tue":113,"Wed":98,"Thu":97,"Fri":92,"Sat":103,"Sun":94,"Workday":101,"7 Day":100,"Count":3114},"10:15:00":{"Mon":106,"Tue":105,"Wed":114,"Thu":92,"Fri":94,"Sat":101,"Sun":99,"Workday":101,"7 Day":101,"Count":3128},"10:30:00":{"Mon":112,"Tue":112,"Wed":104,"Thu":90,"Fri":94,"Sat":111,"Sun":104,"Workday":101,"7 Day":103,"Count":3206},"10:45:00":{"Mon":108,"Tue":104,"Wed":110,"Thu":96,"Fri":98,"Sat":113,"Sun":114,"Workday":103,"7 Day":106,"Count":3284},"11:00:00":{"Mon":104,"Tue":114,"Wed":95,"Thu":96,"Fri":100,"Sat":114,"Sun":122,"Workday":102,"7 Day":106,"Count":3294},"11:15:00":{"Mon":112,"Tue":112,"Wed":104,"Thu":95,"Fri":96,"Sat":117,"Sun":125,"Workday":103,"7 Day":108,"Count":3349},"11:30:00":{"Mon":112,"Tue":110,"Wed":107,"Thu":97,"Fri":102,"Sat":121,"Sun":141,"Workday":105,"7 Day":112,"Count":3482},"11:45:00":{"Mon":114,"Tue":111,"Wed":116,"Thu":100,"Fri":105,"Sat":119,"Sun":138,"Workday":109,"7 Day":114,"Count":3543},"12:00:00":{"Mon":112,"Tue":116,"Wed":112,"Thu":98,"Fri":105,"Sat":125,"Sun":146,"Workday":108,"7 Day":115,"Count":3581},"12:15:00":{"Mon":117,"Tue":116,"Wed":115,"Thu":98,"Fri":105,"Sat":122,"Sun":141,"Workday":109,"7 Day":115,"Count":3583},"12:30:00":{"Mon":113,"Tue":117,"Wed":112,"Thu":102,"Fri":114,"Sat":125,"Sun":149,"Workday":111,"7 Day":118,"Count":3673},"12:45:00":{"Mon":118,"Tue":107,"Wed":118,"Thu":102,"Fri":114,"Sat":128,"Sun":148,"Workday":112,"7 Day":119,"Count":3685},"13:00:00":{"Mon":114,"Tue":116,"Wed":127,"Thu":104,"Fri":110,"Sat":124,"Sun":147,"Workday":114,"7 Day":119,"Count":3705},"13:15:00":{"Mon":120,"Tue":122,"Wed":133,"Thu":99,"Fri":112,"Sat":125,"Sun":148,"Workday":116,"7 Day":122,"Count":3774},"13:30:00":{"Mon":121,"Tue":117,"Wed":127,"Thu":98,"Fri":120,"Sat":124,"Sun":148,"Workday":116,"7 Day":121,"Count":3762},"13:45:00":{"Mon":125,"Tue":122,"Wed":124,"Thu":98,"Fri":123,"Sat":119,"Sun":150,"Workday":118,"7 Day":122,"Count":3783},"14:00:00":{"Mon":125,"Tue":127,"Wed":131,"Thu":98,"Fri":117,"Sat":129,"Sun":146,"Workday":119,"7 Day":124,"Count":3839},"14:15:00":{"Mon":122,"Tue":123,"Wed":132,"Thu":101,"Fri":120,"Sat":123,"Sun":147,"Workday":119,"7 Day":123,"Count":3814},"14:30:00":{"Mon":127,"Tue":129,"Wed":135,"Thu":95,"Fri":118,"Sat":123,"Sun":132,"Workday":120,"7 Day":122,"Count":3776},"14:45:00":{"Mon":130,"Tue":119,"Wed":133,"Thu":101,"Fri":129,"Sat":121,"Sun":146,"Workday":122,"7 Day":124,"Count":3860},"15:00:00":{"Mon":132,"Tue":132,"Wed":137,"Thu":97,"Fri":131,"Sat":102,"Sun":141,"Workday":125,"7 Day":124,"Count":3715},"15:15:00":{"Mon":128,"Tue":137,"Wed":133,"Thu":102,"Fri":127,"Sat":94,"Sun":141,"Workday":124,"7 Day":122,"Count":3679},"15:30:00":{"Mon":137,"Tue":137,"Wed":137,"Thu":101,"Fri":118,"Sat":97,"Sun":150,"Workday":124,"7 Day":124,"Count":3727},"15:45:00":{"Mon":138,"Tue":143,"Wed":144,"Thu":110,"Fri":148,"Sat":126,"Sun":132,"Workday":136,"7 Day":134,"Count":3881},"16:00:00":{"Mon":144,"Tue":145,"Wed":152,"Thu":104,"Fri":154,"Sat":136,"Sun":143,"Workday":138,"7 Day":138,"Count":4010},"16:15:00":{"Mon":148,"Tue":150,"Wed":150,"Thu":104,"Fri":152,"Sat":138,"Sun":143,"Workday":139,"7 Day":140,"Count":4048},"16:30:00":{"Mon":154,"Tue":154,"Wed":152,"Thu":107,"Fri":155,"Sat":135,"Sun":146,"Workday":142,"7 Day":142,"Count":4113},"16:45:00":{"Mon":155,"Tue":154,"Wed":160,"Thu":111,"Fri":150,"Sat":147,"Sun":140,"Workday":144,"7 Day":144,"Count":4182},"17:00:00":{"Mon":143,"Tue":153,"Wed":152,"Thu":115,"Fri":142,"Sat":138,"Sun":140,"Workday":139,"7 Day":139,"Count":4044},"17:15:00":{"Mon":153,"Tue":156,"Wed":146,"Thu":106,"Fri":120,"Sat":140,"Sun":137,"Workday":134,"7 Day":136,"Count":4063},"17:30:00":{"Mon":148,"Tue":150,"Wed":144,"Thu":106,"Fri":119,"Sat":132,"Sun":142,"Workday":131,"7 Day":133,"Count":3986},"17:45:00":{"Mon":149,"Tue":152,"Wed":149,"Thu":105,"Fri":113,"Sat":128,"Sun":136,"Workday":132,"7 Day":132,"Count":3950},"18:00:00":{"Mon":142,"Tue":139,"Wed":140,"Thu":105,"Fri":110,"Sat":132,"Sun":138,"Workday":125,"7 Day":128,"Count":3841},"18:15:00":{"Mon":149,"Tue":136,"Wed":144,"Thu":103,"Fri":109,"Sat":117,"Sun":132,"Workday":126,"7 Day":126,"Count":3777},"18:30:00":{"Mon":129,"Tue":126,"Wed":141,"Thu":99,"Fri":108,"Sat":111,"Sun":124,"Workday":119,"7 Day":119,"Count":3560},"18:45:00":{"Mon":130,"Tue":125,"Wed":131,"Thu":90,"Fri":103,"Sat":104,"Sun":120,"Workday":114,"7 Day":113,"Count":3406},"19:00:00":{"Mon":111,"Tue":125,"Wed":124,"Thu":87,"Fri":100,"Sat":100,"Sun":109,"Workday":108,"7 Day":107,"Count":3208},"19:15:00":{"Mon":108,"Tue":108,"Wed":125,"Thu":83,"Fri":97,"Sat":90,"Sun":109,"Workday":103,"7 Day":102,"Count":3055},"19:30:00":{"Mon":102,"Tue":99,"Wed":119,"Thu":78,"Fri":101,"Sat":94,"Sun":104,"Workday":99,"7 Day":99,"Count":2961},"19:45:00":{"Mon":93,"Tue":94,"Wed":109,"Thu":78,"Fri":92,"Sat":89,"Sun":100,"Workday":92,"7 Day":93,"Count":2791},"20:00:00":{"Mon":84,"Tue":92,"Wed":98,"Thu":80,"Fri":88,"Sat":82,"Sun":94,"Workday":88,"7 Day":88,"Count":2635},"20:15:00":{"Mon":77,"Tue":90,"Wed":102,"Thu":75,"Fri":89,"Sat":79,"Sun":93,"Workday":86,"7 Day":86,"Count":2581},"20:30:00":{"Mon":78,"Tue":84,"Wed":92,"Thu":68,"Fri":78,"Sat":74,"Sun":88,"Workday":79,"7 Day":80,"Count":2393},"20:45:00":{"Mon":72,"Tue":70,"Wed":84,"Thu":61,"Fri":72,"Sat":70,"Sun":79,"Workday":71,"7 Day":72,"Count":2163},"21:00:00":{"Mon":68,"Tue":71,"Wed":80,"Thu":59,"Fri":69,"Sat":64,"Sun":73,"Workday":69,"7 Day":69,"Count":2062},"21:15:00":{"Mon":64,"Tue":77,"Wed":82,"Thu":52,"Fri":60,"Sat":61,"Sun":70,"Workday":66,"7 Day":66,"Count":1977},"21:30:00":{"Mon":62,"Tue":68,"Wed":74,"Thu":54,"Fri":58,"Sat":66,"Sun":55,"Workday":63,"7 Day":62,"Count":1860},"21:45:00":{"Mon":58,"Tue":67,"Wed":70,"Thu":55,"Fri":56,"Sat":57,"Sun":56,"Workday":61,"7 Day":60,"Count":1789},"22:00:00":{"Mon":59,"Tue":62,"Wed":70,"Thu":48,"Fri":51,"Sat":51,"Sun":52,"Workday":57,"7 Day":56,"Count":1671},"22:15:00":{"Mon":57,"Tue":55,"Wed":67,"Thu":46,"Fri":51,"Sat":45,"Sun":47,"Workday":55,"7 Day":52,"Count":1571},"22:30:00":{"Mon":50,"Tue":58,"Wed":57,"Thu":45,"Fri":54,"Sat":41,"Sun":45,"Workday":53,"7 Day":50,"Count":1502},"22:45:00":{"Mon":43,"Tue":50,"Wed":57,"Thu":48,"Fri":56,"Sat":40,"Sun":45,"Workday":51,"7 Day":48,"Count":1458},"23:00:00":{"Mon":42,"Tue":48,"Wed":56,"Thu":41,"Fri":50,"Sat":44,"Sun":34,"Workday":47,"7 Day":45,"Count":1354},"23:15:00":{"Mon":45,"Tue":46,"Wed":50,"Thu":37,"Fri":50,"Sat":46,"Sun":36,"Workday":46,"7 Day":44,"Count":1334},"23:30:00":{"Mon":37,"Tue":34,"Wed":40,"Thu":28,"Fri":40,"Sat":44,"Sun":32,"Workday":36,"7 Day":36,"Count":1088},"23:45:00":{"Mon":22,"Tue":27,"Wed":29,"Thu":26,"Fri":37,"Sat":42,"Sun":30,"Workday":29,"7 Day":31,"Count":916},"07-19":{"Mon":5960,"Tue":6009,"Wed":6013,"Thu":4619,"Fri":5236,"Sat":5186,"Sun":5566,"Workday":5506,"7 Day":5467,"Count":166521},"06-22":{"Mon":7194,"Tue":7283,"Wed":7404,"Thu":5609,"Fri":6370,"Sat":6216,"Sun":6682,"Workday":6698,"7 Day":6625,"Count":201425},"06-24":{"Mon":7549,"Tue":7664,"Wed":7830,"Thu":5929,"Fri":6760,"Sat":6568,"Sun":7005,"Workday":7070,"7 Day":6987,"Count":212319},"00-24":{"Mon":8000,"Tue":8126,"Wed":8336,"Thu":6319,"Fri":7174,"Sat":6984,"Sun":7434,"Workday":7511,"7 Day":7423,"Count":225809},"am Peak":{"Mon":"08:00:00","Tue":"08:00:00","Wed":"08:15:00","Thu":"11:00:00","Fri":"11:00:00","Sat":"11:00:00","Sun":"11:00:00","Workday":"08:15:00","7 Day":"11:00:00","Count":""},"Peak Volume":{"Mon":151,"Tue":154,"Wed":153,"Thu":110,"Fri":153,"Sat":140,"Sun":148,"Workday":141,"7 Day":141,"Count":null},"pm Peak":{"Mon":"16:30:00","Tue":"16:30:00","Wed":"16:00:00","Thu":"16:30:00","Fri":"16:00:00","Sat":"16:30:00","Sun":"13:00:00","Workday":"16:15:00","7 Day":"16:15:00","Count":""}}}